{
  "actionOverrides": [],
  "activateable": false,
  "associateEntityType": null,
  "associateParentEntity": null,
  "childRelationships": [
    {
      "cascadeDelete": true,
      "childSObject": "AIInsightValue",
      "deprecatedAndHidden": false,
      "field": "SobjectLookupValueId",
      "junctionIdListNames": [],
      "junctionReferenceTo": [],
      "relationshipName": null,
      "restrictedDelete": false
    },
    {
      "cascadeDelete": true,
      "childSObject": "AIRecordInsight",
      "deprecatedAndHidden": false,
      "field": "TargetId",
      "junctionIdListNames": [],
      "junctionReferenceTo": [],
      "relationshipName": null,
      "restrictedDelete": false
    },
    {
      "cascadeDelete": true,
      "childSObject": "ActivityHistory",
      "deprecatedAndHidden": false,
      "field": "WhatId",
      "junctionIdListNames": [],
      "junctionReferenceTo": [],
      "relationshipName": "ActivityHistories",
      "restrictedDelete": false
    },
    {
      "cascadeDelete": false,
      "childSObject": "AssessmentTaskContentDocument",
      "deprecatedAndHidden": false,
      "field": "ContentContextId",
      "junctionIdListNames": [],
      "junctionReferenceTo": [],
      "relationshipName": "ContentDocumentContext",
      "restrictedDelete": true
    },
    {
      "cascadeDelete": true,
      "childSObject": "AttachedContentDocument",
      "deprecatedAndHidden": false,
      "field": "LinkedEntityId",
      "junctionIdListNames": [],
      "junctionReferenceTo": [],
      "relationshipName": "AttachedContentDocuments",
      "restrictedDelete": false
    },
    {
      "cascadeDelete": true,
      "childSObject": "Attachment",
      "deprecatedAndHidden": false,
      "field": "ParentId",
      "junctionIdListNames": [],
      "junctionReferenceTo": [],
      "relationshipName": "Attachments",
      "restrictedDelete": false
    },
    {
      "cascadeDelete": true,
      "childSObject": "AuthorNote",
      "deprecatedAndHidden": false,
      "field": "ParentRecordId",
      "junctionIdListNames": [],
      "junctionReferenceTo": [],
      "relationshipName": "RecordAuthorNotes",
      "restrictedDelete": false
    },
    {
      "cascadeDelete": true,
      "childSObject": "ClinicalDetectedIssueDetail",
      "deprecatedAndHidden": false,
      "field": "ClinicalDetectedIssueId",
      "junctionIdListNames": [],
      "junctionReferenceTo": [],
      "relationshipName": "Detail_ClinicalDetectedIssue",
      "restrictedDelete": false
    },
    {
      "cascadeDelete": true,
      "childSObject": "ClinicalDetectedIssueFeed",
      "deprecatedAndHidden": false,
      "field": "ParentId",
      "junctionIdListNames": [],
      "junctionReferenceTo": [],
      "relationshipName": "Feeds",
      "restrictedDelete": false
    },
    {
      "cascadeDelete": true,
      "childSObject": "ClinicalDetectedIssueHistory",
      "deprecatedAndHidden": false,
      "field": "ClinicalDetectedIssueId",
      "junctionIdListNames": [],
      "junctionReferenceTo": [],
      "relationshipName": "Histories",
      "restrictedDelete": false
    },
    {
      "cascadeDelete": true,
      "childSObject": "ClinicalDetectedIssueShare",
      "deprecatedAndHidden": false,
      "field": "ParentId",
      "junctionIdListNames": [],
      "junctionReferenceTo": [],
      "relationshipName": "Shares",
      "restrictedDelete": false
    },
    {
      "cascadeDelete": true,
      "childSObject": "CombinedAttachment",
      "deprecatedAndHidden": false,
      "field": "ParentId",
      "junctionIdListNames": [],
      "junctionReferenceTo": [],
      "relationshipName": "CombinedAttachments",
      "restrictedDelete": false
    },
    {
      "cascadeDelete": true,
      "childSObject": "ContentDocumentLink",
      "deprecatedAndHidden": false,
      "field": "LinkedEntityId",
      "junctionIdListNames": [],
      "junctionReferenceTo": [],
      "relationshipName": "ContentDocumentLinks",
      "restrictedDelete": false
    },
    {
      "cascadeDelete": false,
      "childSObject": "ContentDocumentLinkChangeEvent",
      "deprecatedAndHidden": false,
      "field": "LinkedEntityId",
      "junctionIdListNames": [],
      "junctionReferenceTo": [],
      "relationshipName": null,
      "restrictedDelete": false
    },
    {
      "cascadeDelete": false,
      "childSObject": "ContentVersion",
      "deprecatedAndHidden": false,
      "field": "FirstPublishLocationId",
      "junctionIdListNames": [],
      "junctionReferenceTo": [],
      "relationshipName": null,
      "restrictedDelete": false
    },
    {
      "cascadeDelete": false,
      "childSObject": "ContentVersionChangeEvent",
      "deprecatedAndHidden": false,
      "field": "FirstPublishLocationId",
      "junctionIdListNames": [],
      "junctionReferenceTo": [],
      "relationshipName": null,
      "restrictedDelete": false
    },
    {
      "cascadeDelete": false,
      "childSObject": "EmailMessage",
      "deprecatedAndHidden": false,
      "field": "RelatedToId",
      "junctionIdListNames": [],
      "junctionReferenceTo": [],
      "relationshipName": "Emails",
      "restrictedDelete": false
    },
    {
      "cascadeDelete": false,
      "childSObject": "EmailMessageChangeEvent",
      "deprecatedAndHidden": false,
      "field": "RelatedToId",
      "junctionIdListNames": [],
      "junctionReferenceTo": [],
      "relationshipName": null,
      "restrictedDelete": false
    },
    {
      "cascadeDelete": true,
      "childSObject": "EntitySubscription",
      "deprecatedAndHidden": false,
      "field": "ParentId",
      "junctionIdListNames": [],
      "junctionReferenceTo": [],
      "relationshipName": "FeedSubscriptionsForEntity",
      "restrictedDelete": false
    },
    {
      "cascadeDelete": true,
      "childSObject": "Event",
      "deprecatedAndHidden": false,
      "field": "WhatId",
      "junctionIdListNames": [],
      "junctionReferenceTo": [],
      "relationshipName": "Events",
      "restrictedDelete": false
    },
    {
      "cascadeDelete": false,
      "childSObject": "EventChangeEvent",
      "deprecatedAndHidden": false,
      "field": "WhatId",
      "junctionIdListNames": [],
      "junctionReferenceTo": [],
      "relationshipName": null,
      "restrictedDelete": false
    },
    {
      "cascadeDelete": true,
      "childSObject": "EventRelation",
      "deprecatedAndHidden": false,
      "field": "RelationId",
      "junctionIdListNames": [],
      "junctionReferenceTo": [],
      "relationshipName": "EventRelations",
      "restrictedDelete": false
    },
    {
      "cascadeDelete": false,
      "childSObject": "EventRelationChangeEvent",
      "deprecatedAndHidden": false,
      "field": "RelationId",
      "junctionIdListNames": [],
      "junctionReferenceTo": [],
      "relationshipName": null,
      "restrictedDelete": false
    },
    {
      "cascadeDelete": false,
      "childSObject": "FeedComment",
      "deprecatedAndHidden": false,
      "field": "ParentId",
      "junctionIdListNames": [],
      "junctionReferenceTo": [],
      "relationshipName": null,
      "restrictedDelete": false
    },
    {
      "cascadeDelete": true,
      "childSObject": "FeedItem",
      "deprecatedAndHidden": false,
      "field": "ParentId",
      "junctionIdListNames": [],
      "junctionReferenceTo": [],
      "relationshipName": null,
      "restrictedDelete": false
    },
    {
      "cascadeDelete": false,
      "childSObject": "FlowExecutionErrorEvent",
      "deprecatedAndHidden": false,
      "field": "ContextRecordId",
      "junctionIdListNames": [],
      "junctionReferenceTo": [],
      "relationshipName": null,
      "restrictedDelete": false
    },
    {
      "cascadeDelete": false,
      "childSObject": "FlowOrchestrationWorkItem",
      "deprecatedAndHidden": false,
      "field": "RelatedRecordId",
      "junctionIdListNames": [],
      "junctionReferenceTo": [],
      "relationshipName": null,
      "restrictedDelete": false
    },
    {
      "cascadeDelete": false,
      "childSObject": "FlowRecordRelation",
      "deprecatedAndHidden": false,
      "field": "RelatedRecordId",
      "junctionIdListNames": [],
      "junctionReferenceTo": [],
      "relationshipName": null,
      "restrictedDelete": false
    },
    {
      "cascadeDelete": false,
      "childSObject": "GenericAsmtTaskContext",
      "deprecatedAndHidden": false,
      "field": "ContextId",
      "junctionIdListNames": [],
      "junctionReferenceTo": [],
      "relationshipName": null,
      "restrictedDelete": false
    },
    {
      "cascadeDelete": true,
      "childSObject": "GenericVisitTaskContext",
      "deprecatedAndHidden": false,
      "field": "ContextId",
      "junctionIdListNames": [],
      "junctionReferenceTo": [],
      "relationshipName": "GVTaskContexts",
      "restrictedDelete": false
    },
    {
      "cascadeDelete": true,
      "childSObject": "Identifier",
      "deprecatedAndHidden": false,
      "field": "ParentRecordId",
      "junctionIdListNames": [],
      "junctionReferenceTo": [],
      "relationshipName": "Identifiers",
      "restrictedDelete": false
    },
    {
      "cascadeDelete": false,
      "childSObject": "MedTherapyStmtReviewIssue",
      "deprecatedAndHidden": false,
      "field": "ClinicalDetectedIssueId",
      "junctionIdListNames": [],
      "junctionReferenceTo": [],
      "relationshipName": "MTStmtReviewIssue_ClinicalDetectedIssues",
      "restrictedDelete": true
    },
    {
      "cascadeDelete": false,
      "childSObject": "MedicationDispense",
      "deprecatedAndHidden": false,
      "field": "PrimaryDetectedIssueId",
      "junctionIdListNames": [],
      "junctionReferenceTo": [],
      "relationshipName": "MedicationDispense_PrimaryDetectedIssue",
      "restrictedDelete": false
    },
    {
      "cascadeDelete": false,
      "childSObject": "MedicationDispense",
      "deprecatedAndHidden": false,
      "field": "StatusReasonRelatedIssueId",
      "junctionIdListNames": [],
      "junctionReferenceTo": [],
      "relationshipName": "MedicationDispense_StatusReasonRelatedIssue",
      "restrictedDelete": false
    },
    {
      "cascadeDelete": false,
      "childSObject": "NetworkActivityAudit",
      "deprecatedAndHidden": false,
      "field": "ParentEntityId",
      "junctionIdListNames": [],
      "junctionReferenceTo": [],
      "relationshipName": "ParentEntities",
      "restrictedDelete": false
    },
    {
      "cascadeDelete": false,
      "childSObject": "NetworkFeedResponseMetric",
      "deprecatedAndHidden": false,
      "field": "ParentRecordId",
      "junctionIdListNames": [],
      "junctionReferenceTo": [],
      "relationshipName": null,
      "restrictedDelete": false
    },
    {
      "cascadeDelete": true,
      "childSObject": "OpenActivity",
      "deprecatedAndHidden": false,
      "field": "WhatId",
      "junctionIdListNames": [],
      "junctionReferenceTo": [],
      "relationshipName": "OpenActivities",
      "restrictedDelete": false
    },
    {
      "cascadeDelete": false,
      "childSObject": "OutgoingEmail",
      "deprecatedAndHidden": false,
      "field": "RelatedToId",
      "junctionIdListNames": [],
      "junctionReferenceTo": [],
      "relationshipName": null,
      "restrictedDelete": false
    },
    {
      "cascadeDelete": true,
      "childSObject": "ProcessInstance",
      "deprecatedAndHidden": false,
      "field": "TargetObjectId",
      "junctionIdListNames": [],
      "junctionReferenceTo": [],
      "relationshipName": "ProcessInstances",
      "restrictedDelete": false
    },
    {
      "cascadeDelete": false,
      "childSObject": "ProcessInstanceHistory",
      "deprecatedAndHidden": false,
      "field": "TargetObjectId",
      "junctionIdListNames": [],
      "junctionReferenceTo": [],
      "relationshipName": "ProcessSteps",
      "restrictedDelete": false
    },
    {
      "cascadeDelete": true,
      "childSObject": "Task",
      "deprecatedAndHidden": false,
      "field": "WhatId",
      "junctionIdListNames": [],
      "junctionReferenceTo": [],
      "relationshipName": "Tasks",
      "restrictedDelete": false
    },
    {
      "cascadeDelete": false,
      "childSObject": "TaskChangeEvent",
      "deprecatedAndHidden": false,
      "field": "WhatId",
      "junctionIdListNames": [],
      "junctionReferenceTo": [],
      "relationshipName": null,
      "restrictedDelete": false
    },
    {
      "cascadeDelete": true,
      "childSObject": "TaskRelation",
      "deprecatedAndHidden": false,
      "field": "RelationId",
      "junctionIdListNames": [],
      "junctionReferenceTo": [],
      "relationshipName": "TaskRelations",
      "restrictedDelete": false
    },
    {
      "cascadeDelete": false,
      "childSObject": "TaskRelationChangeEvent",
      "deprecatedAndHidden": false,
      "field": "RelationId",
      "junctionIdListNames": [],
      "junctionReferenceTo": [],
      "relationshipName": null,
      "restrictedDelete": false
    }
  ],
  "compactLayoutable": true,
  "createable": false,
  "custom": false,
  "customSetting": false,
  "deepCloneable": false,
  "defaultImplementation": null,
  "deletable": false,
  "deprecatedAndHidden": false,
  "extendedBy": null,
  "extendsInterfaces": null,
  "feedEnabled": false,
  "fields": [
    {
      "aggregatable": true,
      "aiPredictionField": false,
      "autoNumber": false,
      "byteLength": 18,
      "calculated": false,
      "calculatedFormula": null,
      "cascadeDelete": false,
      "caseSensitive": false,
      "compoundFieldName": null,
      "controllerName": null,
      "createable": false,
      "custom": false,
      "defaultValue": null,
      "defaultValueFormula": null,
      "defaultedOnCreate": true,
      "dependentPicklist": false,
      "deprecatedAndHidden": false,
      "digits": 0,
      "displayLocationInDecimal": false,
      "encrypted": false,
      "externalId": false,
      "extraTypeInfo": null,
      "filterable": true,
      "filteredLookupInfo": null,
      "formulaTreatNullNumberAsZero": false,
      "groupable": true,
      "highScaleNumber": false,
      "htmlFormatted": false,
      "idLookup": true,
      "inlineHelpText": null,
      "label": "ID problema rilevato clinico",
      "length": 18,
      "mask": null,
      "maskType": null,
      "name": "Id",
      "nameField": false,
      "namePointing": false,
      "nillable": false,
      "permissionable": false,
      "picklistValues": [],
      "polymorphicForeignKey": false,
      "precision": 0,
      "queryByDistance": false,
      "referenceTargetField": null,
      "referenceTo": [],
      "relationshipName": null,
      "relationshipOrder": null,
      "restrictedDelete": false,
      "restrictedPicklist": false,
      "scale": 0,
      "searchPrefilterable": false,
      "soapType": "tns:ID",
      "sortable": true,
      "type": "id",
      "unique": false,
      "updateable": false,
      "writeRequiresMasterRead": false
    },
    {
      "aggregatable": true,
      "aiPredictionField": false,
      "autoNumber": false,
      "byteLength": 18,
      "calculated": false,
      "calculatedFormula": null,
      "cascadeDelete": false,
      "caseSensitive": false,
      "compoundFieldName": null,
      "controllerName": null,
      "createable": false,
      "custom": false,
      "defaultValue": "02d1x0000004CRCAA2",
      "defaultValueFormula": null,
      "defaultedOnCreate": true,
      "dependentPicklist": false,
      "deprecatedAndHidden": false,
      "digits": 0,
      "displayLocationInDecimal": false,
      "encrypted": false,
      "externalId": false,
      "extraTypeInfo": null,
      "filterable": true,
      "filteredLookupInfo": null,
      "formulaTreatNullNumberAsZero": false,
      "groupable": true,
      "highScaleNumber": false,
      "htmlFormatted": false,
      "idLookup": false,
      "inlineHelpText": null,
      "label": "ID divisione",
      "length": 18,
      "mask": null,
      "maskType": null,
      "name": "Division",
      "nameField": false,
      "namePointing": false,
      "nillable": false,
      "permissionable": false,
      "picklistValues": [
        {
          "active": true,
          "defaultValue": true,
          "label": "Globale",
          "validFor": null,
          "value": "02d1x0000004CRCAA2"
        }
      ],
      "polymorphicForeignKey": false,
      "precision": 0,
      "queryByDistance": false,
      "referenceTargetField": null,
      "referenceTo": [],
      "relationshipName": null,
      "relationshipOrder": null,
      "restrictedDelete": false,
      "restrictedPicklist": true,
      "scale": 0,
      "searchPrefilterable": false,
      "soapType": "xsd:string",
      "sortable": true,
      "type": "picklist",
      "unique": false,
      "updateable": false,
      "writeRequiresMasterRead": false
    },
    {
      "aggregatable": true,
      "aiPredictionField": false,
      "autoNumber": false,
      "byteLength": 18,
      "calculated": false,
      "calculatedFormula": null,
      "cascadeDelete": false,
      "caseSensitive": false,
      "compoundFieldName": null,
      "controllerName": null,
      "createable": false,
      "custom": false,
      "defaultValue": null,
      "defaultValueFormula": null,
      "defaultedOnCreate": false,
      "dependentPicklist": false,
      "deprecatedAndHidden": false,
      "digits": 0,
      "displayLocationInDecimal": false,
      "encrypted": false,
      "externalId": false,
      "extraTypeInfo": null,
      "filterable": true,
      "filteredLookupInfo": null,
      "formulaTreatNullNumberAsZero": false,
      "groupable": true,
      "highScaleNumber": false,
      "htmlFormatted": false,
      "idLookup": false,
      "inlineHelpText": null,
      "label": "ID titolare",
      "length": 18,
      "mask": null,
      "maskType": null,
      "name": "OwnerId",
      "nameField": false,
      "namePointing": true,
      "nillable": false,
      "permissionable": false,
      "picklistValues": [],
      "polymorphicForeignKey": true,
      "precision": 0,
      "queryByDistance": false,
      "referenceTargetField": null,
      "referenceTo": [
        "Group",
        "User"
      ],
      "relationshipName": "Owner",
      "relationshipOrder": null,
      "restrictedDelete": false,
      "restrictedPicklist": false,
      "scale": 0,
      "searchPrefilterable": false,
      "soapType": "tns:ID",
      "sortable": true,
      "type": "reference",
      "unique": false,
      "updateable": false,
      "writeRequiresMasterRead": false
    },
    {
      "aggregatable": false,
      "aiPredictionField": false,
      "autoNumber": false,
      "byteLength": 0,
      "calculated": false,
      "calculatedFormula": null,
      "cascadeDelete": false,
      "caseSensitive": false,
      "compoundFieldName": null,
      "controllerName": null,
      "createable": false,
      "custom": false,
      "defaultValue": false,
      "defaultValueFormula": null,
      "defaultedOnCreate": true,
      "dependentPicklist": false,
      "deprecatedAndHidden": false,
      "digits": 0,
      "displayLocationInDecimal": false,
      "encrypted": false,
      "externalId": false,
      "extraTypeInfo": null,
      "filterable": true,
      "filteredLookupInfo": null,
      "formulaTreatNullNumberAsZero": false,
      "groupable": true,
      "highScaleNumber": false,
      "htmlFormatted": false,
      "idLookup": false,
      "inlineHelpText": null,
      "label": "Eliminato",
      "length": 0,
      "mask": null,
      "maskType": null,
      "name": "IsDeleted",
      "nameField": false,
      "namePointing": false,
      "nillable": false,
      "permissionable": false,
      "picklistValues": [],
      "polymorphicForeignKey": false,
      "precision": 0,
      "queryByDistance": false,
      "referenceTargetField": null,
      "referenceTo": [],
      "relationshipName": null,
      "relationshipOrder": null,
      "restrictedDelete": false,
      "restrictedPicklist": false,
      "scale": 0,
      "searchPrefilterable": false,
      "soapType": "xsd:boolean",
      "sortable": true,
      "type": "boolean",
      "unique": false,
      "updateable": false,
      "writeRequiresMasterRead": false
    },
    {
      "aggregatable": true,
      "aiPredictionField": false,
      "autoNumber": true,
      "byteLength": 765,
      "calculated": false,
      "calculatedFormula": null,
      "cascadeDelete": false,
      "caseSensitive": false,
      "compoundFieldName": null,
      "controllerName": null,
      "createable": false,
      "custom": false,
      "defaultValue": null,
      "defaultValueFormula": null,
      "defaultedOnCreate": true,
      "dependentPicklist": false,
      "deprecatedAndHidden": false,
      "digits": 0,
      "displayLocationInDecimal": false,
      "encrypted": false,
      "externalId": false,
      "extraTypeInfo": null,
      "filterable": true,
      "filteredLookupInfo": null,
      "formulaTreatNullNumberAsZero": false,
      "groupable": false,
      "highScaleNumber": false,
      "htmlFormatted": false,
      "idLookup": true,
      "inlineHelpText": null,
      "label": "Nome",
      "length": 255,
      "mask": null,
      "maskType": null,
      "name": "Name",
      "nameField": true,
      "namePointing": false,
      "nillable": false,
      "permissionable": false,
      "picklistValues": [],
      "polymorphicForeignKey": false,
      "precision": 0,
      "queryByDistance": false,
      "referenceTargetField": null,
      "referenceTo": [],
      "relationshipName": null,
      "relationshipOrder": null,
      "restrictedDelete": false,
      "restrictedPicklist": false,
      "scale": 0,
      "searchPrefilterable": false,
      "soapType": "xsd:string",
      "sortable": true,
      "type": "string",
      "unique": false,
      "updateable": false,
      "writeRequiresMasterRead": false
    },
    {
      "aggregatable": true,
      "aiPredictionField": false,
      "autoNumber": false,
      "byteLength": 9,
      "calculated": false,
      "calculatedFormula": null,
      "cascadeDelete": false,
      "caseSensitive": false,
      "compoundFieldName": null,
      "controllerName": null,
      "createable": false,
      "custom": false,
      "defaultValue": "EUR",
      "defaultValueFormula": null,
      "defaultedOnCreate": true,
      "dependentPicklist": false,
      "deprecatedAndHidden": false,
      "digits": 0,
      "displayLocationInDecimal": false,
      "encrypted": false,
      "externalId": false,
      "extraTypeInfo": null,
      "filterable": true,
      "filteredLookupInfo": null,
      "formulaTreatNullNumberAsZero": false,
      "groupable": true,
      "highScaleNumber": false,
      "htmlFormatted": false,
      "idLookup": false,
      "inlineHelpText": null,
      "label": "Codice ISO valuta",
      "length": 3,
      "mask": null,
      "maskType": null,
      "name": "CurrencyIsoCode",
      "nameField": false,
      "namePointing": false,
      "nillable": false,
      "permissionable": false,
      "picklistValues": [
        {
          "active": true,
          "defaultValue": true,
          "label": "Euro",
          "validFor": null,
          "value": "EUR"
        }
      ],
      "polymorphicForeignKey": false,
      "precision": 0,
      "queryByDistance": false,
      "referenceTargetField": null,
      "referenceTo": [],
      "relationshipName": null,
      "relationshipOrder": null,
      "restrictedDelete": false,
      "restrictedPicklist": true,
      "scale": 0,
      "searchPrefilterable": false,
      "soapType": "xsd:string",
      "sortable": true,
      "type": "picklist",
      "unique": false,
      "updateable": false,
      "writeRequiresMasterRead": false
    },
    {
      "aggregatable": true,
      "aiPredictionField": false,
      "autoNumber": false,
      "byteLength": 0,
      "calculated": false,
      "calculatedFormula": null,
      "cascadeDelete": false,
      "caseSensitive": false,
      "compoundFieldName": null,
      "controllerName": null,
      "createable": false,
      "custom": false,
      "defaultValue": null,
      "defaultValueFormula": null,
      "defaultedOnCreate": true,
      "dependentPicklist": false,
      "deprecatedAndHidden": false,
      "digits": 0,
      "displayLocationInDecimal": false,
      "encrypted": false,
      "externalId": false,
      "extraTypeInfo": null,
      "filterable": true,
      "filteredLookupInfo": null,
      "formulaTreatNullNumberAsZero": false,
      "groupable": false,
      "highScaleNumber": false,
      "htmlFormatted": false,
      "idLookup": false,
      "inlineHelpText": null,
      "label": "Data creazione",
      "length": 0,
      "mask": null,
      "maskType": null,
      "name": "CreatedDate",
      "nameField": false,
      "namePointing": false,
      "nillable": false,
      "permissionable": false,
      "picklistValues": [],
      "polymorphicForeignKey": false,
      "precision": 0,
      "queryByDistance": false,
      "referenceTargetField": null,
      "referenceTo": [],
      "relationshipName": null,
      "relationshipOrder": null,
      "restrictedDelete": false,
      "restrictedPicklist": false,
      "scale": 0,
      "searchPrefilterable": false,
      "soapType": "xsd:dateTime",
      "sortable": true,
      "type": "datetime",
      "unique": false,
      "updateable": false,
      "writeRequiresMasterRead": false
    },
    {
      "aggregatable": true,
      "aiPredictionField": false,
      "autoNumber": false,
      "byteLength": 18,
      "calculated": false,
      "calculatedFormula": null,
      "cascadeDelete": false,
      "caseSensitive": false,
      "compoundFieldName": null,
      "controllerName": null,
      "createable": false,
      "custom": false,
      "defaultValue": null,
      "defaultValueFormula": null,
      "defaultedOnCreate": true,
      "dependentPicklist": false,
      "deprecatedAndHidden": false,
      "digits": 0,
      "displayLocationInDecimal": false,
      "encrypted": false,
      "externalId": false,
      "extraTypeInfo": null,
      "filterable": true,
      "filteredLookupInfo": null,
      "formulaTreatNullNumberAsZero": false,
      "groupable": true,
      "highScaleNumber": false,
      "htmlFormatted": false,
      "idLookup": false,
      "inlineHelpText": null,
      "label": "Creato da ID",
      "length": 18,
      "mask": null,
      "maskType": null,
      "name": "CreatedById",
      "nameField": false,
      "namePointing": false,
      "nillable": false,
      "permissionable": false,
      "picklistValues": [],
      "polymorphicForeignKey": false,
      "precision": 0,
      "queryByDistance": false,
      "referenceTargetField": null,
      "referenceTo": [
        "User"
      ],
      "relationshipName": "CreatedBy",
      "relationshipOrder": null,
      "restrictedDelete": false,
      "restrictedPicklist": false,
      "scale": 0,
      "searchPrefilterable": false,
      "soapType": "tns:ID",
      "sortable": true,
      "type": "reference",
      "unique": false,
      "updateable": false,
      "writeRequiresMasterRead": false
    },
    {
      "aggregatable": true,
      "aiPredictionField": false,
      "autoNumber": false,
      "byteLength": 0,
      "calculated": false,
      "calculatedFormula": null,
      "cascadeDelete": false,
      "caseSensitive": false,
      "compoundFieldName": null,
      "controllerName": null,
      "createable": false,
      "custom": false,
      "defaultValue": null,
      "defaultValueFormula": null,
      "defaultedOnCreate": true,
      "dependentPicklist": false,
      "deprecatedAndHidden": false,
      "digits": 0,
      "displayLocationInDecimal": false,
      "encrypted": false,
      "externalId": false,
      "extraTypeInfo": null,
      "filterable": true,
      "filteredLookupInfo": null,
      "formulaTreatNullNumberAsZero": false,
      "groupable": false,
      "highScaleNumber": false,
      "htmlFormatted": false,
      "idLookup": false,
      "inlineHelpText": null,
      "label": "Data ultima modifica",
      "length": 0,
      "mask": null,
      "maskType": null,
      "name": "LastModifiedDate",
      "nameField": false,
      "namePointing": false,
      "nillable": false,
      "permissionable": false,
      "picklistValues": [],
      "polymorphicForeignKey": false,
      "precision": 0,
      "queryByDistance": false,
      "referenceTargetField": null,
      "referenceTo": [],
      "relationshipName": null,
      "relationshipOrder": null,
      "restrictedDelete": false,
      "restrictedPicklist": false,
      "scale": 0,
      "searchPrefilterable": false,
      "soapType": "xsd:dateTime",
      "sortable": true,
      "type": "datetime",
      "unique": false,
      "updateable": false,
      "writeRequiresMasterRead": false
    },
    {
      "aggregatable": true,
      "aiPredictionField": false,
      "autoNumber": false,
      "byteLength": 18,
      "calculated": false,
      "calculatedFormula": null,
      "cascadeDelete": false,
      "caseSensitive": false,
      "compoundFieldName": null,
      "controllerName": null,
      "createable": false,
      "custom": false,
      "defaultValue": null,
      "defaultValueFormula": null,
      "defaultedOnCreate": true,
      "dependentPicklist": false,
      "deprecatedAndHidden": false,
      "digits": 0,
      "displayLocationInDecimal": false,
      "encrypted": false,
      "externalId": false,
      "extraTypeInfo": null,
      "filterable": true,
      "filteredLookupInfo": null,
      "formulaTreatNullNumberAsZero": false,
      "groupable": true,
      "highScaleNumber": false,
      "htmlFormatted": false,
      "idLookup": false,
      "inlineHelpText": null,
      "label": "ID ultima modifica di",
      "length": 18,
      "mask": null,
      "maskType": null,
      "name": "LastModifiedById",
      "nameField": false,
      "namePointing": false,
      "nillable": false,
      "permissionable": false,
      "picklistValues": [],
      "polymorphicForeignKey": false,
      "precision": 0,
      "queryByDistance": false,
      "referenceTargetField": null,
      "referenceTo": [
        "User"
      ],
      "relationshipName": "LastModifiedBy",
      "relationshipOrder": null,
      "restrictedDelete": false,
      "restrictedPicklist": false,
      "scale": 0,
      "searchPrefilterable": false,
      "soapType": "tns:ID",
      "sortable": true,
      "type": "reference",
      "unique": false,
      "updateable": false,
      "writeRequiresMasterRead": false
    },
    {
      "aggregatable": true,
      "aiPredictionField": false,
      "autoNumber": false,
      "byteLength": 0,
      "calculated": false,
      "calculatedFormula": null,
      "cascadeDelete": false,
      "caseSensitive": false,
      "compoundFieldName": null,
      "controllerName": null,
      "createable": false,
      "custom": false,
      "defaultValue": null,
      "defaultValueFormula": null,
      "defaultedOnCreate": true,
      "dependentPicklist": false,
      "deprecatedAndHidden": false,
      "digits": 0,
      "displayLocationInDecimal": false,
      "encrypted": false,
      "externalId": false,
      "extraTypeInfo": null,
      "filterable": true,
      "filteredLookupInfo": null,
      "formulaTreatNullNumberAsZero": false,
      "groupable": false,
      "highScaleNumber": false,
      "htmlFormatted": false,
      "idLookup": false,
      "inlineHelpText": null,
      "label": "Modstamp di sistema",
      "length": 0,
      "mask": null,
      "maskType": null,
      "name": "SystemModstamp",
      "nameField": false,
      "namePointing": false,
      "nillable": false,
      "permissionable": false,
      "picklistValues": [],
      "polymorphicForeignKey": false,
      "precision": 0,
      "queryByDistance": false,
      "referenceTargetField": null,
      "referenceTo": [],
      "relationshipName": null,
      "relationshipOrder": null,
      "restrictedDelete": false,
      "restrictedPicklist": false,
      "scale": 0,
      "searchPrefilterable": false,
      "soapType": "xsd:dateTime",
      "sortable": true,
      "type": "datetime",
      "unique": false,
      "updateable": false,
      "writeRequiresMasterRead": false
    },
    {
      "aggregatable": true,
      "aiPredictionField": false,
      "autoNumber": false,
      "byteLength": 0,
      "calculated": false,
      "calculatedFormula": null,
      "cascadeDelete": false,
      "caseSensitive": false,
      "compoundFieldName": null,
      "controllerName": null,
      "createable": false,
      "custom": false,
      "defaultValue": null,
      "defaultValueFormula": null,
      "defaultedOnCreate": false,
      "dependentPicklist": false,
      "deprecatedAndHidden": false,
      "digits": 0,
      "displayLocationInDecimal": false,
      "encrypted": false,
      "externalId": false,
      "extraTypeInfo": null,
      "filterable": true,
      "filteredLookupInfo": null,
      "formulaTreatNullNumberAsZero": false,
      "groupable": false,
      "highScaleNumber": false,
      "htmlFormatted": false,
      "idLookup": false,
      "inlineHelpText": null,
      "label": "Data ultima visualizzazione",
      "length": 0,
      "mask": null,
      "maskType": null,
      "name": "LastViewedDate",
      "nameField": false,
      "namePointing": false,
      "nillable": true,
      "permissionable": false,
      "picklistValues": [],
      "polymorphicForeignKey": false,
      "precision": 0,
      "queryByDistance": false,
      "referenceTargetField": null,
      "referenceTo": [],
      "relationshipName": null,
      "relationshipOrder": null,
      "restrictedDelete": false,
      "restrictedPicklist": false,
      "scale": 0,
      "searchPrefilterable": false,
      "soapType": "xsd:dateTime",
      "sortable": true,
      "type": "datetime",
      "unique": false,
      "updateable": false,
      "writeRequiresMasterRead": false
    },
    {
      "aggregatable": true,
      "aiPredictionField": false,
      "autoNumber": false,
      "byteLength": 0,
      "calculated": false,
      "calculatedFormula": null,
      "cascadeDelete": false,
      "caseSensitive": false,
      "compoundFieldName": null,
      "controllerName": null,
      "createable": false,
      "custom": false,
      "defaultValue": null,
      "defaultValueFormula": null,
      "defaultedOnCreate": false,
      "dependentPicklist": false,
      "deprecatedAndHidden": false,
      "digits": 0,
      "displayLocationInDecimal": false,
      "encrypted": false,
      "externalId": false,
      "extraTypeInfo": null,
      "filterable": true,
      "filteredLookupInfo": null,
      "formulaTreatNullNumberAsZero": false,
      "groupable": false,
      "highScaleNumber": false,
      "htmlFormatted": false,
      "idLookup": false,
      "inlineHelpText": null,
      "label": "Data ultimo riferimento",
      "length": 0,
      "mask": null,
      "maskType": null,
      "name": "LastReferencedDate",
      "nameField": false,
      "namePointing": false,
      "nillable": true,
      "permissionable": false,
      "picklistValues": [],
      "polymorphicForeignKey": false,
      "precision": 0,
      "queryByDistance": false,
      "referenceTargetField": null,
      "referenceTo": [],
      "relationshipName": null,
      "relationshipOrder": null,
      "restrictedDelete": false,
      "restrictedPicklist": false,
      "scale": 0,
      "searchPrefilterable": false,
      "soapType": "xsd:dateTime",
      "sortable": true,
      "type": "datetime",
      "unique": false,
      "updateable": false,
      "writeRequiresMasterRead": false
    },
    {
      "aggregatable": true,
      "aiPredictionField": false,
      "autoNumber": false,
      "byteLength": 18,
      "calculated": false,
      "calculatedFormula": null,
      "cascadeDelete": false,
      "caseSensitive": false,
      "compoundFieldName": null,
      "controllerName": null,
      "createable": false,
      "custom": false,
      "defaultValue": null,
      "defaultValueFormula": null,
      "defaultedOnCreate": false,
      "dependentPicklist": false,
      "deprecatedAndHidden": false,
      "digits": 0,
      "displayLocationInDecimal": false,
      "encrypted": false,
      "externalId": false,
      "extraTypeInfo": null,
      "filterable": true,
      "filteredLookupInfo": null,
      "formulaTreatNullNumberAsZero": false,
      "groupable": true,
      "highScaleNumber": false,
      "htmlFormatted": false,
      "idLookup": false,
      "inlineHelpText": null,
      "label": "ID account",
      "length": 18,
      "mask": null,
      "maskType": null,
      "name": "PatientId",
      "nameField": false,
      "namePointing": false,
      "nillable": false,
      "permissionable": false,
      "picklistValues": [],
      "polymorphicForeignKey": false,
      "precision": 0,
      "queryByDistance": false,
      "referenceTargetField": null,
      "referenceTo": [
        "Account"
      ],
      "relationshipName": "Patient",
      "relationshipOrder": null,
      "restrictedDelete": false,
      "restrictedPicklist": false,
      "scale": 0,
      "searchPrefilterable": true,
      "soapType": "tns:ID",
      "sortable": true,
      "type": "reference",
      "unique": false,
      "updateable": false,
      "writeRequiresMasterRead": false
    },
    {
      "aggregatable": true,
      "aiPredictionField": false,
      "autoNumber": false,
      "byteLength": 120,
      "calculated": false,
      "calculatedFormula": null,
      "cascadeDelete": false,
      "caseSensitive": false,
      "compoundFieldName": null,
      "controllerName": null,
      "createable": false,
      "custom": false,
      "defaultValue": null,
      "defaultValueFormula": null,
      "defaultedOnCreate": false,
      "dependentPicklist": false,
      "deprecatedAndHidden": false,
      "digits": 0,
      "displayLocationInDecimal": false,
      "encrypted": false,
      "externalId": false,
      "extraTypeInfo": null,
      "filterable": true,
      "filteredLookupInfo": null,
      "formulaTreatNullNumberAsZero": false,
      "groupable": true,
      "highScaleNumber": false,
      "htmlFormatted": false,
      "idLookup": false,
      "inlineHelpText": null,
      "label": "Stato",
      "length": 40,
      "mask": null,
      "maskType": null,
      "name": "Status",
      "nameField": false,
      "namePointing": false,
      "nillable": false,
      "permissionable": false,
      "picklistValues": [
        {
          "active": true,
          "defaultValue": false,
          "label": "Registrato",
          "validFor": null,
          "value": "Registrato"
        },
        {
          "active": true,
          "defaultValue": false,
          "label": "Preliminare",
          "validFor": null,
          "value": "Preliminare"
        },
        {
          "active": true,
          "defaultValue": false,
          "label": "Finale",
          "validFor": null,
          "value": "Finale"
        },
        {
          "active": true,
          "defaultValue": false,
          "label": "Modificato",
          "validFor": null,
          "value": "Modificato"
        },
        {
          "active": true,
          "defaultValue": false,
          "label": "Corretto",
          "validFor": null,
          "value": "Corretto"
        },
        {
          "active": true,
          "defaultValue": false,
          "label": "Annullato",
          "validFor": null,
          "value": "Annullato"
        },
        {
          "active": true,
          "defaultValue": false,
          "label": "Immessa per errore",
          "validFor": null,
          "value": "Immessa per errore"
        },
        {
          "active": true,
          "defaultValue": false,
          "label": "Sconosciuto",
          "validFor": null,
          "value": "Sconosciuto"
        }
      ],
      "polymorphicForeignKey": false,
      "precision": 0,
      "queryByDistance": false,
      "referenceTargetField": null,
      "referenceTo": [],
      "relationshipName": null,
      "relationshipOrder": null,
      "restrictedDelete": false,
      "restrictedPicklist": false,
      "scale": 0,
      "searchPrefilterable": false,
      "soapType": "xsd:string",
      "sortable": true,
      "type": "picklist",
      "unique": false,
      "updateable": false,
      "writeRequiresMasterRead": false
    },
    {
      "aggregatable": true,
      "aiPredictionField": false,
      "autoNumber": false,
      "byteLength": 18,
      "calculated": false,
      "calculatedFormula": null,
      "cascadeDelete": false,
      "caseSensitive": false,
      "compoundFieldName": null,
      "controllerName": null,
      "createable": false,
      "custom": false,
      "defaultValue": null,
      "defaultValueFormula": null,
      "defaultedOnCreate": false,
      "dependentPicklist": false,
      "deprecatedAndHidden": false,
      "digits": 0,
      "displayLocationInDecimal": false,
      "encrypted": false,
      "externalId": false,
      "extraTypeInfo": null,
      "filterable": true,
      "filteredLookupInfo": null,
      "formulaTreatNullNumberAsZero": false,
      "groupable": true,
      "highScaleNumber": false,
      "htmlFormatted": false,
      "idLookup": false,
      "inlineHelpText": "Il codice che rappresenta la categoria del problema rilevato clinico.",
      "label": "ID codice categoria",
      "length": 18,
      "mask": null,
      "maskType": null,
      "name": "CategoryCodeId",
      "nameField": false,
      "namePointing": true,
      "nillable": true,
      "permissionable": true,
      "picklistValues": [],
      "polymorphicForeignKey": true,
      "precision": 0,
      "queryByDistance": false,
      "referenceTargetField": null,
      "referenceTo": [
        "CodeSet",
        "CodeSetBundle"
      ],
      "relationshipName": "CategoryCode",
      "relationshipOrder": null,
      "restrictedDelete": false,
      "restrictedPicklist": false,
      "scale": 0,
      "searchPrefilterable": true,
      "soapType": "tns:ID",
      "sortable": true,
      "type": "reference",
      "unique": false,
      "updateable": false,
      "writeRequiresMasterRead": false
    },
    {
      "aggregatable": true,
      "aiPredictionField": false,
      "autoNumber": false,
      "byteLength": 120,
      "calculated": false,
      "calculatedFormula": null,
      "cascadeDelete": false,
      "caseSensitive": false,
      "compoundFieldName": null,
      "controllerName": null,
      "createable": false,
      "custom": false,
      "defaultValue": null,
      "defaultValueFormula": null,
      "defaultedOnCreate": false,
      "dependentPicklist": false,
      "deprecatedAndHidden": false,
      "digits": 0,
      "displayLocationInDecimal": false,
      "encrypted": false,
      "externalId": false,
      "extraTypeInfo": null,
      "filterable": true,
      "filteredLookupInfo": null,
      "formulaTreatNullNumberAsZero": false,
      "groupable": true,
      "highScaleNumber": false,
      "htmlFormatted": false,
      "idLookup": false,
      "inlineHelpText": null,
      "label": "Livello di gravità",
      "length": 40,
      "mask": null,
      "maskType": null,
      "name": "SeverityLevel",
      "nameField": false,
      "namePointing": false,
      "nillable": true,
      "permissionable": true,
      "picklistValues": [
        {
          "active": true,
          "defaultValue": false,
          "label": "Alta",
          "validFor": null,
          "value": "Alta"
        },
        {
          "active": true,
          "defaultValue": false,
          "label": "Moderata",
          "validFor": null,
          "value": "Moderata"
        },
        {
          "active": true,
          "defaultValue": false,
          "label": "Bassa",
          "validFor": null,
          "value": "Bassa"
        }
      ],
      "polymorphicForeignKey": false,
      "precision": 0,
      "queryByDistance": false,
      "referenceTargetField": null,
      "referenceTo": [],
      "relationshipName": null,
      "relationshipOrder": null,
      "restrictedDelete": false,
      "restrictedPicklist": false,
      "scale": 0,
      "searchPrefilterable": false,
      "soapType": "xsd:string",
      "sortable": true,
      "type": "picklist",
      "unique": false,
      "updateable": false,
      "writeRequiresMasterRead": false
    },
    {
      "aggregatable": true,
      "aiPredictionField": false,
      "autoNumber": false,
      "byteLength": 0,
      "calculated": false,
      "calculatedFormula": null,
      "cascadeDelete": false,
      "caseSensitive": false,
      "compoundFieldName": null,
      "controllerName": null,
      "createable": false,
      "custom": false,
      "defaultValue": null,
      "defaultValueFormula": null,
      "defaultedOnCreate": false,
      "dependentPicklist": false,
      "deprecatedAndHidden": false,
      "digits": 0,
      "displayLocationInDecimal": false,
      "encrypted": false,
      "externalId": false,
      "extraTypeInfo": null,
      "filterable": true,
      "filteredLookupInfo": null,
      "formulaTreatNullNumberAsZero": false,
      "groupable": false,
      "highScaleNumber": false,
      "htmlFormatted": false,
      "idLookup": false,
      "inlineHelpText": null,
      "label": "Data iniziale identificazione",
      "length": 0,
      "mask": null,
      "maskType": null,
      "name": "IdentificationStartDateTime",
      "nameField": false,
      "namePointing": false,
      "nillable": true,
      "permissionable": true,
      "picklistValues": [],
      "polymorphicForeignKey": false,
      "precision": 0,
      "queryByDistance": false,
      "referenceTargetField": null,
      "referenceTo": [],
      "relationshipName": null,
      "relationshipOrder": null,
      "restrictedDelete": false,
      "restrictedPicklist": false,
      "scale": 0,
      "searchPrefilterable": false,
      "soapType": "xsd:dateTime",
      "sortable": true,
      "type": "datetime",
      "unique": false,
      "updateable": false,
      "writeRequiresMasterRead": false
    },
    {
      "aggregatable": true,
      "aiPredictionField": false,
      "autoNumber": false,
      "byteLength": 0,
      "calculated": false,
      "calculatedFormula": null,
      "cascadeDelete": false,
      "caseSensitive": false,
      "compoundFieldName": null,
      "controllerName": null,
      "createable": false,
      "custom": false,
      "defaultValue": null,
      "defaultValueFormula": null,
      "defaultedOnCreate": false,
      "dependentPicklist": false,
      "deprecatedAndHidden": false,
      "digits": 0,
      "displayLocationInDecimal": false,
      "encrypted": false,
      "externalId": false,
      "extraTypeInfo": null,
      "filterable": true,
      "filteredLookupInfo": null,
      "formulaTreatNullNumberAsZero": false,
      "groupable": false,
      "highScaleNumber": false,
      "htmlFormatted": false,
      "idLookup": false,
      "inlineHelpText": null,
      "label": "Data finale identificazione",
      "length": 0,
      "mask": null,
      "maskType": null,
      "name": "IdentificationEndDateTime",
      "nameField": false,
      "namePointing": false,
      "nillable": true,
      "permissionable": true,
      "picklistValues": [],
      "polymorphicForeignKey": false,
      "precision": 0,
      "queryByDistance": false,
      "referenceTargetField": null,
      "referenceTo": [],
      "relationshipName": null,
      "relationshipOrder": null,
      "restrictedDelete": false,
      "restrictedPicklist": false,
      "scale": 0,
      "searchPrefilterable": false,
      "soapType": "xsd:dateTime",
      "sortable": true,
      "type": "datetime",
      "unique": false,
      "updateable": false,
      "writeRequiresMasterRead": false
    },
    {
      "aggregatable": true,
      "aiPredictionField": false,
      "autoNumber": false,
      "byteLength": 18,
      "calculated": false,
      "calculatedFormula": null,
      "cascadeDelete": false,
      "caseSensitive": false,
      "compoundFieldName": null,
      "controllerName": null,
      "createable": false,
      "custom": false,
      "defaultValue": null,
      "defaultValueFormula": null,
      "defaultedOnCreate": false,
      "dependentPicklist": false,
      "deprecatedAndHidden": false,
      "digits": 0,
      "displayLocationInDecimal": false,
      "encrypted": false,
      "externalId": false,
      "extraTypeInfo": null,
      "filterable": true,
      "filteredLookupInfo": null,
      "formulaTreatNullNumberAsZero": false,
      "groupable": true,
      "highScaleNumber": false,
      "htmlFormatted": false,
      "idLookup": false,
      "inlineHelpText": null,
      "label": "ID identificato da",
      "length": 18,
      "mask": null,
      "maskType": null,
      "name": "IdentifiedById",
      "nameField": false,
      "namePointing": true,
      "nillable": true,
      "permissionable": true,
      "picklistValues": [],
      "polymorphicForeignKey": true,
      "precision": 0,
      "queryByDistance": false,
      "referenceTargetField": null,
      "referenceTo": [
        "Account",
        "CareRegisteredDevice",
        "HealthcareProvider",
        "User"
      ],
      "relationshipName": "IdentifiedBy",
      "relationshipOrder": null,
      "restrictedDelete": false,
      "restrictedPicklist": false,
      "scale": 0,
      "searchPrefilterable": true,
      "soapType": "tns:ID",
      "sortable": true,
      "type": "reference",
      "unique": false,
      "updateable": false,
      "writeRequiresMasterRead": false
    },
    {
      "aggregatable": true,
      "aiPredictionField": false,
      "autoNumber": false,
      "byteLength": 18,
      "calculated": false,
      "calculatedFormula": null,
      "cascadeDelete": false,
      "caseSensitive": false,
      "compoundFieldName": null,
      "controllerName": null,
      "createable": false,
      "custom": false,
      "defaultValue": null,
      "defaultValueFormula": null,
      "defaultedOnCreate": false,
      "dependentPicklist": false,
      "deprecatedAndHidden": false,
      "digits": 0,
      "displayLocationInDecimal": false,
      "encrypted": false,
      "externalId": false,
      "extraTypeInfo": null,
      "filterable": true,
      "filteredLookupInfo": null,
      "formulaTreatNullNumberAsZero": false,
      "groupable": true,
      "highScaleNumber": false,
      "htmlFormatted": false,
      "idLookup": false,
      "inlineHelpText": null,
      "label": "ID riesame terapia farmacologica",
      "length": 18,
      "mask": null,
      "maskType": null,
      "name": "MedicationTherapyReviewId",
      "nameField": false,
      "namePointing": false,
      "nillable": true,
      "permissionable": true,
      "picklistValues": [],
      "polymorphicForeignKey": false,
      "precision": 0,
      "queryByDistance": false,
      "referenceTargetField": null,
      "referenceTo": [
        "MedicationTherapyReview"
      ],
      "relationshipName": "MedicationTherapyReview",
      "relationshipOrder": null,
      "restrictedDelete": false,
      "restrictedPicklist": false,
      "scale": 0,
      "searchPrefilterable": true,
      "soapType": "tns:ID",
      "sortable": true,
      "type": "reference",
      "unique": false,
      "updateable": false,
      "writeRequiresMasterRead": false
    },
    {
      "aggregatable": false,
      "aiPredictionField": false,
      "autoNumber": false,
      "byteLength": 96000,
      "calculated": false,
      "calculatedFormula": null,
      "cascadeDelete": false,
      "caseSensitive": false,
      "compoundFieldName": null,
      "controllerName": null,
      "createable": false,
      "custom": false,
      "defaultValue": null,
      "defaultValueFormula": null,
      "defaultedOnCreate": false,
      "dependentPicklist": false,
      "deprecatedAndHidden": false,
      "digits": 0,
      "displayLocationInDecimal": false,
      "encrypted": false,
      "externalId": false,
      "extraTypeInfo": "plaintextarea",
      "filterable": false,
      "filteredLookupInfo": null,
      "formulaTreatNullNumberAsZero": false,
      "groupable": false,
      "highScaleNumber": false,
      "htmlFormatted": false,
      "idLookup": false,
      "inlineHelpText": null,
      "label": "Descrizione",
      "length": 32000,
      "mask": null,
      "maskType": null,
      "name": "Description",
      "nameField": false,
      "namePointing": false,
      "nillable": true,
      "permissionable": true,
      "picklistValues": [],
      "polymorphicForeignKey": false,
      "precision": 0,
      "queryByDistance": false,
      "referenceTargetField": null,
      "referenceTo": [],
      "relationshipName": null,
      "relationshipOrder": null,
      "restrictedDelete": false,
      "restrictedPicklist": false,
      "scale": 0,
      "searchPrefilterable": false,
      "soapType": "xsd:string",
      "sortable": false,
      "type": "textarea",
      "unique": false,
      "updateable": false,
      "writeRequiresMasterRead": false
    },
    {
      "aggregatable": false,
      "aiPredictionField": false,
      "autoNumber": false,
      "byteLength": 96000,
      "calculated": false,
      "calculatedFormula": null,
      "cascadeDelete": false,
      "caseSensitive": false,
      "compoundFieldName": null,
      "controllerName": null,
      "createable": false,
      "custom": false,
      "defaultValue": null,
      "defaultValueFormula": null,
      "defaultedOnCreate": false,
      "dependentPicklist": false,
      "deprecatedAndHidden": false,
      "digits": 0,
      "displayLocationInDecimal": false,
      "encrypted": false,
      "externalId": false,
      "extraTypeInfo": "plaintextarea",
      "filterable": false,
      "filteredLookupInfo": null,
      "formulaTreatNullNumberAsZero": false,
      "groupable": false,
      "highScaleNumber": false,
      "htmlFormatted": false,
      "idLookup": false,
      "inlineHelpText": "I riferimenti medici che sono disponibili sul problema rilevato clinico.",
      "label": "URI di riferimento",
      "length": 32000,
      "mask": null,
      "maskType": null,
      "name": "ReferenceUri",
      "nameField": false,
      "namePointing": false,
      "nillable": true,
      "permissionable": true,
      "picklistValues": [],
      "polymorphicForeignKey": false,
      "precision": 0,
      "queryByDistance": false,
      "referenceTargetField": null,
      "referenceTo": [],
      "relationshipName": null,
      "relationshipOrder": null,
      "restrictedDelete": false,
      "restrictedPicklist": false,
      "scale": 0,
      "searchPrefilterable": false,
      "soapType": "xsd:string",
      "sortable": false,
      "type": "textarea",
      "unique": false,
      "updateable": false,
      "writeRequiresMasterRead": false
    },
    {
      "aggregatable": true,
      "aiPredictionField": false,
      "autoNumber": false,
      "byteLength": 192,
      "calculated": false,
      "calculatedFormula": null,
      "cascadeDelete": false,
      "caseSensitive": false,
      "compoundFieldName": null,
      "controllerName": null,
      "createable": false,
      "custom": false,
      "defaultValue": null,
      "defaultValueFormula": null,
      "defaultedOnCreate": false,
      "dependentPicklist": false,
      "deprecatedAndHidden": false,
      "digits": 0,
      "displayLocationInDecimal": false,
      "encrypted": false,
      "externalId": false,
      "extraTypeInfo": null,
      "filterable": true,
      "filteredLookupInfo": null,
      "formulaTreatNullNumberAsZero": false,
      "groupable": true,
      "highScaleNumber": false,
      "htmlFormatted": false,
      "idLookup": false,
      "inlineHelpText": null,
      "label": "Sistema di origine",
      "length": 64,
      "mask": null,
      "maskType": null,
      "name": "SourceSystem",
      "nameField": false,
      "namePointing": false,
      "nillable": true,
      "permissionable": true,
      "picklistValues": [],
      "polymorphicForeignKey": false,
      "precision": 0,
      "queryByDistance": false,
      "referenceTargetField": null,
      "referenceTo": [],
      "relationshipName": null,
      "relationshipOrder": null,
      "restrictedDelete": false,
      "restrictedPicklist": false,
      "scale": 0,
      "searchPrefilterable": false,
      "soapType": "xsd:string",
      "sortable": true,
      "type": "string",
      "unique": false,
      "updateable": false,
      "writeRequiresMasterRead": false
    },
    {
      "aggregatable": true,
      "aiPredictionField": false,
      "autoNumber": false,
      "byteLength": 765,
      "calculated": false,
      "calculatedFormula": null,
      "cascadeDelete": false,
      "caseSensitive": false,
      "compoundFieldName": null,
      "controllerName": null,
      "createable": false,
      "custom": false,
      "defaultValue": null,
      "defaultValueFormula": null,
      "defaultedOnCreate": false,
      "dependentPicklist": false,
      "deprecatedAndHidden": false,
      "digits": 0,
      "displayLocationInDecimal": false,
      "encrypted": false,
      "externalId": false,
      "extraTypeInfo": null,
      "filterable": true,
      "filteredLookupInfo": null,
      "formulaTreatNullNumberAsZero": false,
      "groupable": true,
      "highScaleNumber": false,
      "htmlFormatted": false,
      "idLookup": false,
      "inlineHelpText": null,
      "label": "ID sistema di origine",
      "length": 255,
      "mask": null,
      "maskType": null,
      "name": "SourceSystemIdentifier",
      "nameField": false,
      "namePointing": false,
      "nillable": true,
      "permissionable": true,
      "picklistValues": [],
      "polymorphicForeignKey": false,
      "precision": 0,
      "queryByDistance": false,
      "referenceTargetField": null,
      "referenceTo": [],
      "relationshipName": null,
      "relationshipOrder": null,
      "restrictedDelete": false,
      "restrictedPicklist": false,
      "scale": 0,
      "searchPrefilterable": false,
      "soapType": "xsd:string",
      "sortable": true,
      "type": "string",
      "unique": false,
      "updateable": false,
      "writeRequiresMasterRead": false
    },
    {
      "aggregatable": true,
      "aiPredictionField": false,
      "autoNumber": false,
      "byteLength": 0,
      "calculated": false,
      "calculatedFormula": null,
      "cascadeDelete": false,
      "caseSensitive": false,
      "compoundFieldName": null,
      "controllerName": null,
      "createable": false,
      "custom": false,
      "defaultValue": null,
      "defaultValueFormula": null,
      "defaultedOnCreate": false,
      "dependentPicklist": false,
      "deprecatedAndHidden": false,
      "digits": 0,
      "displayLocationInDecimal": false,
      "encrypted": false,
      "externalId": false,
      "extraTypeInfo": null,
      "filterable": true,
      "filteredLookupInfo": null,
      "formulaTreatNullNumberAsZero": false,
      "groupable": false,
      "highScaleNumber": false,
      "htmlFormatted": false,
      "idLookup": false,
      "inlineHelpText": "La data più recente in cui il sistema di integrazione ha scritto il record dal record di origine.",
      "label": "Data modifica nel sistema di origine",
      "length": 0,
      "mask": null,
      "maskType": null,
      "name": "SourceSysModifiedDateTime",
      "nameField": false,
      "namePointing": false,
      "nillable": true,
      "permissionable": true,
      "picklistValues": [],
      "polymorphicForeignKey": false,
      "precision": 0,
      "queryByDistance": false,
      "referenceTargetField": null,
      "referenceTo": [],
      "relationshipName": null,
      "relationshipOrder": null,
      "restrictedDelete": false,
      "restrictedPicklist": false,
      "scale": 0,
      "searchPrefilterable": false,
      "soapType": "xsd:dateTime",
      "sortable": true,
      "type": "datetime",
      "unique": false,
      "updateable": false,
      "writeRequiresMasterRead": false
    }
  ],
  "hasSubtypes": false,
  "implementedBy": null,
  "implementsInterfaces": null,
  "isInterface": false,
  "isSubtype": false,
  "keyPrefix": "0u5",
  "label": "Problema rilevato clinico",
  "labelPlural": "Problemi rilevati clinici",
  "layoutable": true,
  "listviewable": null,
  "lookupLayoutable": null,
  "mergeable": false,
  "mruEnabled": true,
  "name": "ClinicalDetectedIssue",
  "namedLayoutInfos": [],
  "networkScopeFieldName": null,
  "queryable": true,
  "recordTypeInfos": [
    {
      "active": true,
      "available": true,
      "defaultRecordTypeMapping": true,
      "developerName": "Principale",
      "master": true,
      "name": "Principale",
      "recordTypeId": "012000000000000AAA",
      "urls": {
        "layout": "/services/data/v56.0/sobjects/ClinicalDetectedIssue/describe/layouts/012000000000000AAA"
      }
    }
  ],
  "replicateable": true,
  "retrieveable": true,
  "searchLayoutable": true,
  "searchable": true,
  "sobjectDescribeOption": "FULL",
  "supportedScopes": [
    {
      "label": "Tutti i problemi rilevati clinici",
      "name": "everything"
    },
    {
      "label": "Problemi rilevati clinici personali",
      "name": "mine"
    },
    {
      "label": "Problemi rilevati clinici di proprietà dell'area di attesa",
      "name": "queue_owned"
    },
    {
      "label": "Problemi rilevati clinici del team personale",
      "name": "team"
    },
    {
      "label": "Problemi rilevati clinici di proprietà dell'utente",
      "name": "user_owned"
    }
  ],
  "triggerable": true,
  "undeletable": false,
  "updateable": false,
  "urls": {
    "compactLayouts": "/services/data/v56.0/sobjects/ClinicalDetectedIssue/describe/compactLayouts",
    "rowTemplate": "/services/data/v56.0/sobjects/ClinicalDetectedIssue/{ID}",
    "approvalLayouts": "/services/data/v56.0/sobjects/ClinicalDetectedIssue/describe/approvalLayouts",
    "uiDetailTemplate": "https://flow-flow-8123.scratch.my.salesforce.com/{ID}",
    "uiEditTemplate": "https://flow-flow-8123.scratch.my.salesforce.com/{ID}/e",
    "describe": "/services/data/v56.0/sobjects/ClinicalDetectedIssue/describe",
    "uiNewRecord": "https://flow-flow-8123.scratch.my.salesforce.com/0u5/e",
    "quickActions": "/services/data/v56.0/sobjects/ClinicalDetectedIssue/quickActions",
    "layouts": "/services/data/v56.0/sobjects/ClinicalDetectedIssue/describe/layouts",
    "sobject": "/services/data/v56.0/sobjects/ClinicalDetectedIssue"
  }
}
