{
  "actionOverrides": [],
  "activateable": false,
  "associateEntityType": null,
  "associateParentEntity": null,
  "childRelationships": [
    {
      "cascadeDelete": true,
      "childSObject": "AIInsightValue",
      "deprecatedAndHidden": false,
      "field": "SobjectLookupValueId",
      "junctionIdListNames": [],
      "junctionReferenceTo": [],
      "relationshipName": null,
      "restrictedDelete": false
    },
    {
      "cascadeDelete": true,
      "childSObject": "AIRecordInsight",
      "deprecatedAndHidden": false,
      "field": "TargetId",
      "junctionIdListNames": [],
      "junctionReferenceTo": [],
      "relationshipName": null,
      "restrictedDelete": false
    },
    {
      "cascadeDelete": true,
      "childSObject": "ActivityHistory",
      "deprecatedAndHidden": false,
      "field": "WhatId",
      "junctionIdListNames": [],
      "junctionReferenceTo": [],
      "relationshipName": "ActivityHistories",
      "restrictedDelete": false
    },
    {
      "cascadeDelete": false,
      "childSObject": "AssessmentTaskContentDocument",
      "deprecatedAndHidden": false,
      "field": "ContentContextId",
      "junctionIdListNames": [],
      "junctionReferenceTo": [],
      "relationshipName": "ContentDocumentContext",
      "restrictedDelete": true
    },
    {
      "cascadeDelete": true,
      "childSObject": "AttachedContentDocument",
      "deprecatedAndHidden": false,
      "field": "LinkedEntityId",
      "junctionIdListNames": [],
      "junctionReferenceTo": [],
      "relationshipName": "AttachedContentDocuments",
      "restrictedDelete": false
    },
    {
      "cascadeDelete": true,
      "childSObject": "Attachment",
      "deprecatedAndHidden": false,
      "field": "ParentId",
      "junctionIdListNames": [],
      "junctionReferenceTo": [],
      "relationshipName": "Attachments",
      "restrictedDelete": false
    },
    {
      "cascadeDelete": true,
      "childSObject": "CombinedAttachment",
      "deprecatedAndHidden": false,
      "field": "ParentId",
      "junctionIdListNames": [],
      "junctionReferenceTo": [],
      "relationshipName": "CombinedAttachments",
      "restrictedDelete": false
    },
    {
      "cascadeDelete": true,
      "childSObject": "ContentDocumentLink",
      "deprecatedAndHidden": false,
      "field": "LinkedEntityId",
      "junctionIdListNames": [],
      "junctionReferenceTo": [],
      "relationshipName": "ContentDocumentLinks",
      "restrictedDelete": false
    },
    {
      "cascadeDelete": false,
      "childSObject": "ContentDocumentLinkChangeEvent",
      "deprecatedAndHidden": false,
      "field": "LinkedEntityId",
      "junctionIdListNames": [],
      "junctionReferenceTo": [],
      "relationshipName": null,
      "restrictedDelete": false
    },
    {
      "cascadeDelete": false,
      "childSObject": "ContentVersion",
      "deprecatedAndHidden": false,
      "field": "FirstPublishLocationId",
      "junctionIdListNames": [],
      "junctionReferenceTo": [],
      "relationshipName": null,
      "restrictedDelete": false
    },
    {
      "cascadeDelete": false,
      "childSObject": "ContentVersionChangeEvent",
      "deprecatedAndHidden": false,
      "field": "FirstPublishLocationId",
      "junctionIdListNames": [],
      "junctionReferenceTo": [],
      "relationshipName": null,
      "restrictedDelete": false
    },
    {
      "cascadeDelete": false,
      "childSObject": "EmailMessage",
      "deprecatedAndHidden": false,
      "field": "RelatedToId",
      "junctionIdListNames": [],
      "junctionReferenceTo": [],
      "relationshipName": "Emails",
      "restrictedDelete": false
    },
    {
      "cascadeDelete": false,
      "childSObject": "EmailMessageChangeEvent",
      "deprecatedAndHidden": false,
      "field": "RelatedToId",
      "junctionIdListNames": [],
      "junctionReferenceTo": [],
      "relationshipName": null,
      "restrictedDelete": false
    },
    {
      "cascadeDelete": true,
      "childSObject": "EntitySubscription",
      "deprecatedAndHidden": false,
      "field": "ParentId",
      "junctionIdListNames": [],
      "junctionReferenceTo": [],
      "relationshipName": "FeedSubscriptionsForEntity",
      "restrictedDelete": false
    },
    {
      "cascadeDelete": true,
      "childSObject": "Event",
      "deprecatedAndHidden": false,
      "field": "WhatId",
      "junctionIdListNames": [],
      "junctionReferenceTo": [],
      "relationshipName": "Events",
      "restrictedDelete": false
    },
    {
      "cascadeDelete": false,
      "childSObject": "EventChangeEvent",
      "deprecatedAndHidden": false,
      "field": "WhatId",
      "junctionIdListNames": [],
      "junctionReferenceTo": [],
      "relationshipName": null,
      "restrictedDelete": false
    },
    {
      "cascadeDelete": true,
      "childSObject": "EventRelation",
      "deprecatedAndHidden": false,
      "field": "RelationId",
      "junctionIdListNames": [],
      "junctionReferenceTo": [],
      "relationshipName": "EventRelations",
      "restrictedDelete": false
    },
    {
      "cascadeDelete": false,
      "childSObject": "EventRelationChangeEvent",
      "deprecatedAndHidden": false,
      "field": "RelationId",
      "junctionIdListNames": [],
      "junctionReferenceTo": [],
      "relationshipName": null,
      "restrictedDelete": false
    },
    {
      "cascadeDelete": false,
      "childSObject": "FeedComment",
      "deprecatedAndHidden": false,
      "field": "ParentId",
      "junctionIdListNames": [],
      "junctionReferenceTo": [],
      "relationshipName": null,
      "restrictedDelete": false
    },
    {
      "cascadeDelete": true,
      "childSObject": "FeedItem",
      "deprecatedAndHidden": false,
      "field": "ParentId",
      "junctionIdListNames": [],
      "junctionReferenceTo": [],
      "relationshipName": null,
      "restrictedDelete": false
    },
    {
      "cascadeDelete": false,
      "childSObject": "FlowExecutionErrorEvent",
      "deprecatedAndHidden": false,
      "field": "ContextRecordId",
      "junctionIdListNames": [],
      "junctionReferenceTo": [],
      "relationshipName": null,
      "restrictedDelete": false
    },
    {
      "cascadeDelete": false,
      "childSObject": "FlowOrchestrationWorkItem",
      "deprecatedAndHidden": false,
      "field": "RelatedRecordId",
      "junctionIdListNames": [],
      "junctionReferenceTo": [],
      "relationshipName": null,
      "restrictedDelete": false
    },
    {
      "cascadeDelete": false,
      "childSObject": "FlowRecordRelation",
      "deprecatedAndHidden": false,
      "field": "RelatedRecordId",
      "junctionIdListNames": [],
      "junctionReferenceTo": [],
      "relationshipName": null,
      "restrictedDelete": false
    },
    {
      "cascadeDelete": false,
      "childSObject": "GenericAsmtTaskContext",
      "deprecatedAndHidden": false,
      "field": "ContextId",
      "junctionIdListNames": [],
      "junctionReferenceTo": [],
      "relationshipName": null,
      "restrictedDelete": false
    },
    {
      "cascadeDelete": true,
      "childSObject": "GenericVisitTaskContext",
      "deprecatedAndHidden": false,
      "field": "ContextId",
      "junctionIdListNames": [],
      "junctionReferenceTo": [],
      "relationshipName": "GVTaskContexts",
      "restrictedDelete": false
    },
    {
      "cascadeDelete": false,
      "childSObject": "NetworkActivityAudit",
      "deprecatedAndHidden": false,
      "field": "ParentEntityId",
      "junctionIdListNames": [],
      "junctionReferenceTo": [],
      "relationshipName": "ParentEntities",
      "restrictedDelete": false
    },
    {
      "cascadeDelete": false,
      "childSObject": "NetworkFeedResponseMetric",
      "deprecatedAndHidden": false,
      "field": "ParentRecordId",
      "junctionIdListNames": [],
      "junctionReferenceTo": [],
      "relationshipName": null,
      "restrictedDelete": false
    },
    {
      "cascadeDelete": true,
      "childSObject": "Note",
      "deprecatedAndHidden": false,
      "field": "ParentId",
      "junctionIdListNames": [],
      "junctionReferenceTo": [],
      "relationshipName": "Notes",
      "restrictedDelete": false
    },
    {
      "cascadeDelete": true,
      "childSObject": "NoteAndAttachment",
      "deprecatedAndHidden": false,
      "field": "ParentId",
      "junctionIdListNames": [],
      "junctionReferenceTo": [],
      "relationshipName": "NotesAndAttachments",
      "restrictedDelete": false
    },
    {
      "cascadeDelete": true,
      "childSObject": "OpenActivity",
      "deprecatedAndHidden": false,
      "field": "WhatId",
      "junctionIdListNames": [],
      "junctionReferenceTo": [],
      "relationshipName": "OpenActivities",
      "restrictedDelete": false
    },
    {
      "cascadeDelete": false,
      "childSObject": "OutgoingEmail",
      "deprecatedAndHidden": false,
      "field": "RelatedToId",
      "junctionIdListNames": [],
      "junctionReferenceTo": [],
      "relationshipName": null,
      "restrictedDelete": false
    },
    {
      "cascadeDelete": true,
      "childSObject": "ProcessInstance",
      "deprecatedAndHidden": false,
      "field": "TargetObjectId",
      "junctionIdListNames": [],
      "junctionReferenceTo": [],
      "relationshipName": "ProcessInstances",
      "restrictedDelete": false
    },
    {
      "cascadeDelete": false,
      "childSObject": "ProcessInstanceHistory",
      "deprecatedAndHidden": false,
      "field": "TargetObjectId",
      "junctionIdListNames": [],
      "junctionReferenceTo": [],
      "relationshipName": "ProcessSteps",
      "restrictedDelete": false
    },
    {
      "cascadeDelete": true,
      "childSObject": "SecuritiesHoldingFeed",
      "deprecatedAndHidden": false,
      "field": "ParentId",
      "junctionIdListNames": [],
      "junctionReferenceTo": [],
      "relationshipName": "Feeds",
      "restrictedDelete": false
    },
    {
      "cascadeDelete": true,
      "childSObject": "SecuritiesHoldingHistory",
      "deprecatedAndHidden": false,
      "field": "SecuritiesHoldingId",
      "junctionIdListNames": [],
      "junctionReferenceTo": [],
      "relationshipName": "Histories",
      "restrictedDelete": false
    },
    {
      "cascadeDelete": true,
      "childSObject": "SecuritiesHoldingShare",
      "deprecatedAndHidden": false,
      "field": "ParentId",
      "junctionIdListNames": [],
      "junctionReferenceTo": [],
      "relationshipName": "Shares",
      "restrictedDelete": false
    },
    {
      "cascadeDelete": true,
      "childSObject": "Task",
      "deprecatedAndHidden": false,
      "field": "WhatId",
      "junctionIdListNames": [],
      "junctionReferenceTo": [],
      "relationshipName": "Tasks",
      "restrictedDelete": false
    },
    {
      "cascadeDelete": false,
      "childSObject": "TaskChangeEvent",
      "deprecatedAndHidden": false,
      "field": "WhatId",
      "junctionIdListNames": [],
      "junctionReferenceTo": [],
      "relationshipName": null,
      "restrictedDelete": false
    },
    {
      "cascadeDelete": true,
      "childSObject": "TaskRelation",
      "deprecatedAndHidden": false,
      "field": "RelationId",
      "junctionIdListNames": [],
      "junctionReferenceTo": [],
      "relationshipName": "TaskRelations",
      "restrictedDelete": false
    },
    {
      "cascadeDelete": false,
      "childSObject": "TaskRelationChangeEvent",
      "deprecatedAndHidden": false,
      "field": "RelationId",
      "junctionIdListNames": [],
      "junctionReferenceTo": [],
      "relationshipName": null,
      "restrictedDelete": false
    }
  ],
  "compactLayoutable": true,
  "createable": true,
  "custom": false,
  "customSetting": false,
  "deepCloneable": false,
  "defaultImplementation": null,
  "deletable": true,
  "deprecatedAndHidden": false,
  "extendedBy": null,
  "extendsInterfaces": null,
  "feedEnabled": false,
  "fields": [
    {
      "aggregatable": true,
      "aiPredictionField": false,
      "autoNumber": false,
      "byteLength": 18,
      "calculated": false,
      "calculatedFormula": null,
      "cascadeDelete": false,
      "caseSensitive": false,
      "compoundFieldName": null,
      "controllerName": null,
      "createable": false,
      "custom": false,
      "defaultValue": null,
      "defaultValueFormula": null,
      "defaultedOnCreate": true,
      "dependentPicklist": false,
      "deprecatedAndHidden": false,
      "digits": 0,
      "displayLocationInDecimal": false,
      "encrypted": false,
      "externalId": false,
      "extraTypeInfo": null,
      "filterable": true,
      "filteredLookupInfo": null,
      "formulaTreatNullNumberAsZero": false,
      "groupable": true,
      "highScaleNumber": false,
      "htmlFormatted": false,
      "idLookup": true,
      "inlineHelpText": null,
      "label": "ID portafoglio titoli",
      "length": 18,
      "mask": null,
      "maskType": null,
      "name": "Id",
      "nameField": false,
      "namePointing": false,
      "nillable": false,
      "permissionable": false,
      "picklistValues": [],
      "polymorphicForeignKey": false,
      "precision": 0,
      "queryByDistance": false,
      "referenceTargetField": null,
      "referenceTo": [],
      "relationshipName": null,
      "relationshipOrder": null,
      "restrictedDelete": false,
      "restrictedPicklist": false,
      "scale": 0,
      "searchPrefilterable": false,
      "soapType": "tns:ID",
      "sortable": true,
      "type": "id",
      "unique": false,
      "updateable": false,
      "writeRequiresMasterRead": false
    },
    {
      "aggregatable": true,
      "aiPredictionField": false,
      "autoNumber": false,
      "byteLength": 18,
      "calculated": false,
      "calculatedFormula": null,
      "cascadeDelete": false,
      "caseSensitive": false,
      "compoundFieldName": null,
      "controllerName": null,
      "createable": true,
      "custom": false,
      "defaultValue": null,
      "defaultValueFormula": null,
      "defaultedOnCreate": true,
      "dependentPicklist": false,
      "deprecatedAndHidden": false,
      "digits": 0,
      "displayLocationInDecimal": false,
      "encrypted": false,
      "externalId": false,
      "extraTypeInfo": null,
      "filterable": true,
      "filteredLookupInfo": null,
      "formulaTreatNullNumberAsZero": false,
      "groupable": true,
      "highScaleNumber": false,
      "htmlFormatted": false,
      "idLookup": false,
      "inlineHelpText": null,
      "label": "ID titolare",
      "length": 18,
      "mask": null,
      "maskType": null,
      "name": "OwnerId",
      "nameField": false,
      "namePointing": true,
      "nillable": false,
      "permissionable": false,
      "picklistValues": [],
      "polymorphicForeignKey": true,
      "precision": 0,
      "queryByDistance": false,
      "referenceTargetField": null,
      "referenceTo": [
        "Group",
        "User"
      ],
      "relationshipName": "Owner",
      "relationshipOrder": null,
      "restrictedDelete": false,
      "restrictedPicklist": false,
      "scale": 0,
      "searchPrefilterable": false,
      "soapType": "tns:ID",
      "sortable": true,
      "type": "reference",
      "unique": false,
      "updateable": true,
      "writeRequiresMasterRead": false
    },
    {
      "aggregatable": false,
      "aiPredictionField": false,
      "autoNumber": false,
      "byteLength": 0,
      "calculated": false,
      "calculatedFormula": null,
      "cascadeDelete": false,
      "caseSensitive": false,
      "compoundFieldName": null,
      "controllerName": null,
      "createable": false,
      "custom": false,
      "defaultValue": false,
      "defaultValueFormula": null,
      "defaultedOnCreate": true,
      "dependentPicklist": false,
      "deprecatedAndHidden": false,
      "digits": 0,
      "displayLocationInDecimal": false,
      "encrypted": false,
      "externalId": false,
      "extraTypeInfo": null,
      "filterable": true,
      "filteredLookupInfo": null,
      "formulaTreatNullNumberAsZero": false,
      "groupable": true,
      "highScaleNumber": false,
      "htmlFormatted": false,
      "idLookup": false,
      "inlineHelpText": null,
      "label": "Eliminato",
      "length": 0,
      "mask": null,
      "maskType": null,
      "name": "IsDeleted",
      "nameField": false,
      "namePointing": false,
      "nillable": false,
      "permissionable": false,
      "picklistValues": [],
      "polymorphicForeignKey": false,
      "precision": 0,
      "queryByDistance": false,
      "referenceTargetField": null,
      "referenceTo": [],
      "relationshipName": null,
      "relationshipOrder": null,
      "restrictedDelete": false,
      "restrictedPicklist": false,
      "scale": 0,
      "searchPrefilterable": false,
      "soapType": "xsd:boolean",
      "sortable": true,
      "type": "boolean",
      "unique": false,
      "updateable": false,
      "writeRequiresMasterRead": false
    },
    {
      "aggregatable": true,
      "aiPredictionField": false,
      "autoNumber": false,
      "byteLength": 765,
      "calculated": false,
      "calculatedFormula": null,
      "cascadeDelete": false,
      "caseSensitive": false,
      "compoundFieldName": null,
      "controllerName": null,
      "createable": true,
      "custom": false,
      "defaultValue": null,
      "defaultValueFormula": null,
      "defaultedOnCreate": false,
      "dependentPicklist": false,
      "deprecatedAndHidden": false,
      "digits": 0,
      "displayLocationInDecimal": false,
      "encrypted": false,
      "externalId": false,
      "extraTypeInfo": null,
      "filterable": true,
      "filteredLookupInfo": null,
      "formulaTreatNullNumberAsZero": false,
      "groupable": true,
      "highScaleNumber": false,
      "htmlFormatted": false,
      "idLookup": true,
      "inlineHelpText": null,
      "label": "Nome",
      "length": 255,
      "mask": null,
      "maskType": null,
      "name": "Name",
      "nameField": true,
      "namePointing": false,
      "nillable": false,
      "permissionable": false,
      "picklistValues": [],
      "polymorphicForeignKey": false,
      "precision": 0,
      "queryByDistance": false,
      "referenceTargetField": null,
      "referenceTo": [],
      "relationshipName": null,
      "relationshipOrder": null,
      "restrictedDelete": false,
      "restrictedPicklist": false,
      "scale": 0,
      "searchPrefilterable": false,
      "soapType": "xsd:string",
      "sortable": true,
      "type": "string",
      "unique": false,
      "updateable": true,
      "writeRequiresMasterRead": false
    },
    {
      "aggregatable": true,
      "aiPredictionField": false,
      "autoNumber": false,
      "byteLength": 9,
      "calculated": false,
      "calculatedFormula": null,
      "cascadeDelete": false,
      "caseSensitive": false,
      "compoundFieldName": null,
      "controllerName": null,
      "createable": true,
      "custom": false,
      "defaultValue": "EUR",
      "defaultValueFormula": null,
      "defaultedOnCreate": true,
      "dependentPicklist": false,
      "deprecatedAndHidden": false,
      "digits": 0,
      "displayLocationInDecimal": false,
      "encrypted": false,
      "externalId": false,
      "extraTypeInfo": null,
      "filterable": true,
      "filteredLookupInfo": null,
      "formulaTreatNullNumberAsZero": false,
      "groupable": true,
      "highScaleNumber": false,
      "htmlFormatted": false,
      "idLookup": false,
      "inlineHelpText": null,
      "label": "Codice ISO valuta",
      "length": 3,
      "mask": null,
      "maskType": null,
      "name": "CurrencyIsoCode",
      "nameField": false,
      "namePointing": false,
      "nillable": true,
      "permissionable": false,
      "picklistValues": [
        {
          "active": true,
          "defaultValue": true,
          "label": "Euro",
          "validFor": null,
          "value": "EUR"
        }
      ],
      "polymorphicForeignKey": false,
      "precision": 0,
      "queryByDistance": false,
      "referenceTargetField": null,
      "referenceTo": [],
      "relationshipName": null,
      "relationshipOrder": null,
      "restrictedDelete": false,
      "restrictedPicklist": true,
      "scale": 0,
      "searchPrefilterable": false,
      "soapType": "xsd:string",
      "sortable": true,
      "type": "picklist",
      "unique": false,
      "updateable": true,
      "writeRequiresMasterRead": false
    },
    {
      "aggregatable": true,
      "aiPredictionField": false,
      "autoNumber": false,
      "byteLength": 0,
      "calculated": false,
      "calculatedFormula": null,
      "cascadeDelete": false,
      "caseSensitive": false,
      "compoundFieldName": null,
      "controllerName": null,
      "createable": false,
      "custom": false,
      "defaultValue": null,
      "defaultValueFormula": null,
      "defaultedOnCreate": true,
      "dependentPicklist": false,
      "deprecatedAndHidden": false,
      "digits": 0,
      "displayLocationInDecimal": false,
      "encrypted": false,
      "externalId": false,
      "extraTypeInfo": null,
      "filterable": true,
      "filteredLookupInfo": null,
      "formulaTreatNullNumberAsZero": false,
      "groupable": false,
      "highScaleNumber": false,
      "htmlFormatted": false,
      "idLookup": false,
      "inlineHelpText": null,
      "label": "Data creazione",
      "length": 0,
      "mask": null,
      "maskType": null,
      "name": "CreatedDate",
      "nameField": false,
      "namePointing": false,
      "nillable": false,
      "permissionable": false,
      "picklistValues": [],
      "polymorphicForeignKey": false,
      "precision": 0,
      "queryByDistance": false,
      "referenceTargetField": null,
      "referenceTo": [],
      "relationshipName": null,
      "relationshipOrder": null,
      "restrictedDelete": false,
      "restrictedPicklist": false,
      "scale": 0,
      "searchPrefilterable": false,
      "soapType": "xsd:dateTime",
      "sortable": true,
      "type": "datetime",
      "unique": false,
      "updateable": false,
      "writeRequiresMasterRead": false
    },
    {
      "aggregatable": true,
      "aiPredictionField": false,
      "autoNumber": false,
      "byteLength": 18,
      "calculated": false,
      "calculatedFormula": null,
      "cascadeDelete": false,
      "caseSensitive": false,
      "compoundFieldName": null,
      "controllerName": null,
      "createable": false,
      "custom": false,
      "defaultValue": null,
      "defaultValueFormula": null,
      "defaultedOnCreate": true,
      "dependentPicklist": false,
      "deprecatedAndHidden": false,
      "digits": 0,
      "displayLocationInDecimal": false,
      "encrypted": false,
      "externalId": false,
      "extraTypeInfo": null,
      "filterable": true,
      "filteredLookupInfo": null,
      "formulaTreatNullNumberAsZero": false,
      "groupable": true,
      "highScaleNumber": false,
      "htmlFormatted": false,
      "idLookup": false,
      "inlineHelpText": null,
      "label": "Creato da ID",
      "length": 18,
      "mask": null,
      "maskType": null,
      "name": "CreatedById",
      "nameField": false,
      "namePointing": false,
      "nillable": false,
      "permissionable": false,
      "picklistValues": [],
      "polymorphicForeignKey": false,
      "precision": 0,
      "queryByDistance": false,
      "referenceTargetField": null,
      "referenceTo": [
        "User"
      ],
      "relationshipName": "CreatedBy",
      "relationshipOrder": null,
      "restrictedDelete": false,
      "restrictedPicklist": false,
      "scale": 0,
      "searchPrefilterable": false,
      "soapType": "tns:ID",
      "sortable": true,
      "type": "reference",
      "unique": false,
      "updateable": false,
      "writeRequiresMasterRead": false
    },
    {
      "aggregatable": true,
      "aiPredictionField": false,
      "autoNumber": false,
      "byteLength": 0,
      "calculated": false,
      "calculatedFormula": null,
      "cascadeDelete": false,
      "caseSensitive": false,
      "compoundFieldName": null,
      "controllerName": null,
      "createable": false,
      "custom": false,
      "defaultValue": null,
      "defaultValueFormula": null,
      "defaultedOnCreate": true,
      "dependentPicklist": false,
      "deprecatedAndHidden": false,
      "digits": 0,
      "displayLocationInDecimal": false,
      "encrypted": false,
      "externalId": false,
      "extraTypeInfo": null,
      "filterable": true,
      "filteredLookupInfo": null,
      "formulaTreatNullNumberAsZero": false,
      "groupable": false,
      "highScaleNumber": false,
      "htmlFormatted": false,
      "idLookup": false,
      "inlineHelpText": null,
      "label": "Data ultima modifica",
      "length": 0,
      "mask": null,
      "maskType": null,
      "name": "LastModifiedDate",
      "nameField": false,
      "namePointing": false,
      "nillable": false,
      "permissionable": false,
      "picklistValues": [],
      "polymorphicForeignKey": false,
      "precision": 0,
      "queryByDistance": false,
      "referenceTargetField": null,
      "referenceTo": [],
      "relationshipName": null,
      "relationshipOrder": null,
      "restrictedDelete": false,
      "restrictedPicklist": false,
      "scale": 0,
      "searchPrefilterable": false,
      "soapType": "xsd:dateTime",
      "sortable": true,
      "type": "datetime",
      "unique": false,
      "updateable": false,
      "writeRequiresMasterRead": false
    },
    {
      "aggregatable": true,
      "aiPredictionField": false,
      "autoNumber": false,
      "byteLength": 18,
      "calculated": false,
      "calculatedFormula": null,
      "cascadeDelete": false,
      "caseSensitive": false,
      "compoundFieldName": null,
      "controllerName": null,
      "createable": false,
      "custom": false,
      "defaultValue": null,
      "defaultValueFormula": null,
      "defaultedOnCreate": true,
      "dependentPicklist": false,
      "deprecatedAndHidden": false,
      "digits": 0,
      "displayLocationInDecimal": false,
      "encrypted": false,
      "externalId": false,
      "extraTypeInfo": null,
      "filterable": true,
      "filteredLookupInfo": null,
      "formulaTreatNullNumberAsZero": false,
      "groupable": true,
      "highScaleNumber": false,
      "htmlFormatted": false,
      "idLookup": false,
      "inlineHelpText": null,
      "label": "ID ultima modifica di",
      "length": 18,
      "mask": null,
      "maskType": null,
      "name": "LastModifiedById",
      "nameField": false,
      "namePointing": false,
      "nillable": false,
      "permissionable": false,
      "picklistValues": [],
      "polymorphicForeignKey": false,
      "precision": 0,
      "queryByDistance": false,
      "referenceTargetField": null,
      "referenceTo": [
        "User"
      ],
      "relationshipName": "LastModifiedBy",
      "relationshipOrder": null,
      "restrictedDelete": false,
      "restrictedPicklist": false,
      "scale": 0,
      "searchPrefilterable": false,
      "soapType": "tns:ID",
      "sortable": true,
      "type": "reference",
      "unique": false,
      "updateable": false,
      "writeRequiresMasterRead": false
    },
    {
      "aggregatable": true,
      "aiPredictionField": false,
      "autoNumber": false,
      "byteLength": 0,
      "calculated": false,
      "calculatedFormula": null,
      "cascadeDelete": false,
      "caseSensitive": false,
      "compoundFieldName": null,
      "controllerName": null,
      "createable": false,
      "custom": false,
      "defaultValue": null,
      "defaultValueFormula": null,
      "defaultedOnCreate": true,
      "dependentPicklist": false,
      "deprecatedAndHidden": false,
      "digits": 0,
      "displayLocationInDecimal": false,
      "encrypted": false,
      "externalId": false,
      "extraTypeInfo": null,
      "filterable": true,
      "filteredLookupInfo": null,
      "formulaTreatNullNumberAsZero": false,
      "groupable": false,
      "highScaleNumber": false,
      "htmlFormatted": false,
      "idLookup": false,
      "inlineHelpText": null,
      "label": "Modstamp di sistema",
      "length": 0,
      "mask": null,
      "maskType": null,
      "name": "SystemModstamp",
      "nameField": false,
      "namePointing": false,
      "nillable": false,
      "permissionable": false,
      "picklistValues": [],
      "polymorphicForeignKey": false,
      "precision": 0,
      "queryByDistance": false,
      "referenceTargetField": null,
      "referenceTo": [],
      "relationshipName": null,
      "relationshipOrder": null,
      "restrictedDelete": false,
      "restrictedPicklist": false,
      "scale": 0,
      "searchPrefilterable": false,
      "soapType": "xsd:dateTime",
      "sortable": true,
      "type": "datetime",
      "unique": false,
      "updateable": false,
      "writeRequiresMasterRead": false
    },
    {
      "aggregatable": true,
      "aiPredictionField": false,
      "autoNumber": false,
      "byteLength": 0,
      "calculated": false,
      "calculatedFormula": null,
      "cascadeDelete": false,
      "caseSensitive": false,
      "compoundFieldName": null,
      "controllerName": null,
      "createable": false,
      "custom": false,
      "defaultValue": null,
      "defaultValueFormula": null,
      "defaultedOnCreate": false,
      "dependentPicklist": false,
      "deprecatedAndHidden": false,
      "digits": 0,
      "displayLocationInDecimal": false,
      "encrypted": false,
      "externalId": false,
      "extraTypeInfo": null,
      "filterable": true,
      "filteredLookupInfo": null,
      "formulaTreatNullNumberAsZero": false,
      "groupable": false,
      "highScaleNumber": false,
      "htmlFormatted": false,
      "idLookup": false,
      "inlineHelpText": null,
      "label": "Data ultima visualizzazione",
      "length": 0,
      "mask": null,
      "maskType": null,
      "name": "LastViewedDate",
      "nameField": false,
      "namePointing": false,
      "nillable": true,
      "permissionable": false,
      "picklistValues": [],
      "polymorphicForeignKey": false,
      "precision": 0,
      "queryByDistance": false,
      "referenceTargetField": null,
      "referenceTo": [],
      "relationshipName": null,
      "relationshipOrder": null,
      "restrictedDelete": false,
      "restrictedPicklist": false,
      "scale": 0,
      "searchPrefilterable": false,
      "soapType": "xsd:dateTime",
      "sortable": true,
      "type": "datetime",
      "unique": false,
      "updateable": false,
      "writeRequiresMasterRead": false
    },
    {
      "aggregatable": true,
      "aiPredictionField": false,
      "autoNumber": false,
      "byteLength": 0,
      "calculated": false,
      "calculatedFormula": null,
      "cascadeDelete": false,
      "caseSensitive": false,
      "compoundFieldName": null,
      "controllerName": null,
      "createable": false,
      "custom": false,
      "defaultValue": null,
      "defaultValueFormula": null,
      "defaultedOnCreate": false,
      "dependentPicklist": false,
      "deprecatedAndHidden": false,
      "digits": 0,
      "displayLocationInDecimal": false,
      "encrypted": false,
      "externalId": false,
      "extraTypeInfo": null,
      "filterable": true,
      "filteredLookupInfo": null,
      "formulaTreatNullNumberAsZero": false,
      "groupable": false,
      "highScaleNumber": false,
      "htmlFormatted": false,
      "idLookup": false,
      "inlineHelpText": null,
      "label": "Data ultimo riferimento",
      "length": 0,
      "mask": null,
      "maskType": null,
      "name": "LastReferencedDate",
      "nameField": false,
      "namePointing": false,
      "nillable": true,
      "permissionable": false,
      "picklistValues": [],
      "polymorphicForeignKey": false,
      "precision": 0,
      "queryByDistance": false,
      "referenceTargetField": null,
      "referenceTo": [],
      "relationshipName": null,
      "relationshipOrder": null,
      "restrictedDelete": false,
      "restrictedPicklist": false,
      "scale": 0,
      "searchPrefilterable": false,
      "soapType": "xsd:dateTime",
      "sortable": true,
      "type": "datetime",
      "unique": false,
      "updateable": false,
      "writeRequiresMasterRead": false
    },
    {
      "aggregatable": true,
      "aiPredictionField": false,
      "autoNumber": false,
      "byteLength": 18,
      "calculated": false,
      "calculatedFormula": null,
      "cascadeDelete": false,
      "caseSensitive": false,
      "compoundFieldName": null,
      "controllerName": null,
      "createable": true,
      "custom": false,
      "defaultValue": null,
      "defaultValueFormula": null,
      "defaultedOnCreate": false,
      "dependentPicklist": false,
      "deprecatedAndHidden": false,
      "digits": 0,
      "displayLocationInDecimal": false,
      "encrypted": false,
      "externalId": false,
      "extraTypeInfo": null,
      "filterable": true,
      "filteredLookupInfo": null,
      "formulaTreatNullNumberAsZero": false,
      "groupable": true,
      "highScaleNumber": false,
      "htmlFormatted": false,
      "idLookup": false,
      "inlineHelpText": null,
      "label": "ID account",
      "length": 18,
      "mask": null,
      "maskType": null,
      "name": "PrimaryOwnerId",
      "nameField": false,
      "namePointing": false,
      "nillable": true,
      "permissionable": true,
      "picklistValues": [],
      "polymorphicForeignKey": false,
      "precision": 0,
      "queryByDistance": false,
      "referenceTargetField": null,
      "referenceTo": [
        "Account"
      ],
      "relationshipName": "PrimaryOwner",
      "relationshipOrder": null,
      "restrictedDelete": false,
      "restrictedPicklist": false,
      "scale": 0,
      "searchPrefilterable": true,
      "soapType": "tns:ID",
      "sortable": true,
      "type": "reference",
      "unique": false,
      "updateable": true,
      "writeRequiresMasterRead": false
    },
    {
      "aggregatable": true,
      "aiPredictionField": false,
      "autoNumber": false,
      "byteLength": 18,
      "calculated": false,
      "calculatedFormula": null,
      "cascadeDelete": false,
      "caseSensitive": false,
      "compoundFieldName": null,
      "controllerName": null,
      "createable": true,
      "custom": false,
      "defaultValue": null,
      "defaultValueFormula": null,
      "defaultedOnCreate": false,
      "dependentPicklist": false,
      "deprecatedAndHidden": false,
      "digits": 0,
      "displayLocationInDecimal": false,
      "encrypted": false,
      "externalId": false,
      "extraTypeInfo": null,
      "filterable": true,
      "filteredLookupInfo": null,
      "formulaTreatNullNumberAsZero": false,
      "groupable": true,
      "highScaleNumber": false,
      "htmlFormatted": false,
      "idLookup": false,
      "inlineHelpText": null,
      "label": "ID polizza assicurativa",
      "length": 18,
      "mask": null,
      "maskType": null,
      "name": "InsurancePolicyId",
      "nameField": false,
      "namePointing": false,
      "nillable": true,
      "permissionable": true,
      "picklistValues": [],
      "polymorphicForeignKey": false,
      "precision": 0,
      "queryByDistance": false,
      "referenceTargetField": null,
      "referenceTo": [
        "InsurancePolicy"
      ],
      "relationshipName": "InsurancePolicy",
      "relationshipOrder": null,
      "restrictedDelete": false,
      "restrictedPicklist": false,
      "scale": 0,
      "searchPrefilterable": true,
      "soapType": "tns:ID",
      "sortable": true,
      "type": "reference",
      "unique": false,
      "updateable": true,
      "writeRequiresMasterRead": false
    },
    {
      "aggregatable": true,
      "aiPredictionField": false,
      "autoNumber": false,
      "byteLength": 120,
      "calculated": false,
      "calculatedFormula": null,
      "cascadeDelete": false,
      "caseSensitive": false,
      "compoundFieldName": null,
      "controllerName": null,
      "createable": true,
      "custom": false,
      "defaultValue": null,
      "defaultValueFormula": null,
      "defaultedOnCreate": false,
      "dependentPicklist": false,
      "deprecatedAndHidden": false,
      "digits": 0,
      "displayLocationInDecimal": false,
      "encrypted": false,
      "externalId": false,
      "extraTypeInfo": null,
      "filterable": true,
      "filteredLookupInfo": null,
      "formulaTreatNullNumberAsZero": false,
      "groupable": true,
      "highScaleNumber": false,
      "htmlFormatted": false,
      "idLookup": false,
      "inlineHelpText": null,
      "label": "Classe asset",
      "length": 40,
      "mask": null,
      "maskType": null,
      "name": "AssetClass",
      "nameField": false,
      "namePointing": false,
      "nillable": true,
      "permissionable": true,
      "picklistValues": [
        {
          "active": true,
          "defaultValue": false,
          "label": "Azioni",
          "validFor": null,
          "value": "Azioni"
        },
        {
          "active": true,
          "defaultValue": false,
          "label": "Reddito fisso",
          "validFor": null,
          "value": "Reddito fisso"
        },
        {
          "active": true,
          "defaultValue": false,
          "label": "Equivalenti di liquidità",
          "validFor": null,
          "value": "Equivalenti di liquidità"
        },
        {
          "active": true,
          "defaultValue": false,
          "label": "Investimenti alternativi",
          "validFor": null,
          "value": "Investimenti alternativi"
        }
      ],
      "polymorphicForeignKey": false,
      "precision": 0,
      "queryByDistance": false,
      "referenceTargetField": null,
      "referenceTo": [],
      "relationshipName": null,
      "relationshipOrder": null,
      "restrictedDelete": false,
      "restrictedPicklist": false,
      "scale": 0,
      "searchPrefilterable": false,
      "soapType": "xsd:string",
      "sortable": true,
      "type": "picklist",
      "unique": false,
      "updateable": true,
      "writeRequiresMasterRead": false
    },
    {
      "aggregatable": true,
      "aiPredictionField": false,
      "autoNumber": false,
      "byteLength": 120,
      "calculated": false,
      "calculatedFormula": null,
      "cascadeDelete": false,
      "caseSensitive": false,
      "compoundFieldName": null,
      "controllerName": null,
      "createable": true,
      "custom": false,
      "defaultValue": null,
      "defaultValueFormula": null,
      "defaultedOnCreate": false,
      "dependentPicklist": false,
      "deprecatedAndHidden": false,
      "digits": 0,
      "displayLocationInDecimal": false,
      "encrypted": false,
      "externalId": false,
      "extraTypeInfo": null,
      "filterable": true,
      "filteredLookupInfo": null,
      "formulaTreatNullNumberAsZero": false,
      "groupable": true,
      "highScaleNumber": false,
      "htmlFormatted": false,
      "idLookup": false,
      "inlineHelpText": null,
      "label": "Categoria asset",
      "length": 40,
      "mask": null,
      "maskType": null,
      "name": "AssetCategory",
      "nameField": false,
      "namePointing": false,
      "nillable": true,
      "permissionable": true,
      "picklistValues": [
        {
          "active": true,
          "defaultValue": false,
          "label": "Azioni statunitensi",
          "validFor": null,
          "value": "Azioni statunitensi"
        },
        {
          "active": true,
          "defaultValue": false,
          "label": "Azioni settoriali",
          "validFor": null,
          "value": "Azioni settoriali"
        },
        {
          "active": true,
          "defaultValue": false,
          "label": "Allocazione",
          "validFor": null,
          "value": "Allocazione"
        },
        {
          "active": true,
          "defaultValue": false,
          "label": "Azioni internazionali",
          "validFor": null,
          "value": "Azioni internazionali"
        },
        {
          "active": true,
          "defaultValue": false,
          "label": "Titoli alternativi",
          "validFor": null,
          "value": "Titoli alternativi"
        },
        {
          "active": true,
          "defaultValue": false,
          "label": "Materie prime",
          "validFor": null,
          "value": "Materie prime"
        },
        {
          "active": true,
          "defaultValue": false,
          "label": "Obbligazioni imponibili",
          "validFor": null,
          "value": "Obbligazioni imponibili"
        },
        {
          "active": true,
          "defaultValue": false,
          "label": "Titoli di enti locali",
          "validFor": null,
          "value": "Titoli di enti locali"
        }
      ],
      "polymorphicForeignKey": false,
      "precision": 0,
      "queryByDistance": false,
      "referenceTargetField": null,
      "referenceTo": [],
      "relationshipName": null,
      "relationshipOrder": null,
      "restrictedDelete": false,
      "restrictedPicklist": false,
      "scale": 0,
      "searchPrefilterable": false,
      "soapType": "xsd:string",
      "sortable": true,
      "type": "picklist",
      "unique": false,
      "updateable": true,
      "writeRequiresMasterRead": false
    },
    {
      "aggregatable": true,
      "aiPredictionField": false,
      "autoNumber": false,
      "byteLength": 120,
      "calculated": false,
      "calculatedFormula": null,
      "cascadeDelete": false,
      "caseSensitive": false,
      "compoundFieldName": null,
      "controllerName": null,
      "createable": true,
      "custom": false,
      "defaultValue": null,
      "defaultValueFormula": null,
      "defaultedOnCreate": false,
      "dependentPicklist": false,
      "deprecatedAndHidden": false,
      "digits": 0,
      "displayLocationInDecimal": false,
      "encrypted": false,
      "externalId": false,
      "extraTypeInfo": null,
      "filterable": true,
      "filteredLookupInfo": null,
      "formulaTreatNullNumberAsZero": false,
      "groupable": true,
      "highScaleNumber": false,
      "htmlFormatted": false,
      "idLookup": false,
      "inlineHelpText": null,
      "label": "Nome categoria asset",
      "length": 40,
      "mask": null,
      "maskType": null,
      "name": "AssetCategoryName",
      "nameField": false,
      "namePointing": false,
      "nillable": true,
      "permissionable": true,
      "picklistValues": [
        {
          "active": true,
          "defaultValue": false,
          "label": "Large Growth",
          "validFor": null,
          "value": "Large Growth"
        },
        {
          "active": true,
          "defaultValue": false,
          "label": "Large Value",
          "validFor": null,
          "value": "Large Value"
        },
        {
          "active": true,
          "defaultValue": false,
          "label": "Large Blend",
          "validFor": null,
          "value": "Large Blend"
        },
        {
          "active": true,
          "defaultValue": false,
          "label": "Small Growth",
          "validFor": null,
          "value": "Small Growth"
        },
        {
          "active": true,
          "defaultValue": false,
          "label": "Small Value",
          "validFor": null,
          "value": "Small Value"
        },
        {
          "active": true,
          "defaultValue": false,
          "label": "Small Blend",
          "validFor": null,
          "value": "Small Blend"
        },
        {
          "active": true,
          "defaultValue": false,
          "label": "Mid-Cap Growth",
          "validFor": null,
          "value": "Mid-Cap Growth"
        },
        {
          "active": true,
          "defaultValue": false,
          "label": "Mid-Cap Value",
          "validFor": null,
          "value": "Mid-Cap Value"
        },
        {
          "active": true,
          "defaultValue": false,
          "label": "Mid-Cap Blend",
          "validFor": null,
          "value": "Mid-Cap Blend"
        }
      ],
      "polymorphicForeignKey": false,
      "precision": 0,
      "queryByDistance": false,
      "referenceTargetField": null,
      "referenceTo": [],
      "relationshipName": null,
      "relationshipOrder": null,
      "restrictedDelete": false,
      "restrictedPicklist": false,
      "scale": 0,
      "searchPrefilterable": false,
      "soapType": "xsd:string",
      "sortable": true,
      "type": "picklist",
      "unique": false,
      "updateable": true,
      "writeRequiresMasterRead": false
    },
    {
      "aggregatable": true,
      "aiPredictionField": false,
      "autoNumber": false,
      "byteLength": 0,
      "calculated": false,
      "calculatedFormula": null,
      "cascadeDelete": false,
      "caseSensitive": false,
      "compoundFieldName": null,
      "controllerName": null,
      "createable": true,
      "custom": false,
      "defaultValue": null,
      "defaultValueFormula": null,
      "defaultedOnCreate": false,
      "dependentPicklist": false,
      "deprecatedAndHidden": false,
      "digits": 0,
      "displayLocationInDecimal": false,
      "encrypted": false,
      "externalId": false,
      "extraTypeInfo": null,
      "filterable": true,
      "filteredLookupInfo": null,
      "formulaTreatNullNumberAsZero": false,
      "groupable": false,
      "highScaleNumber": false,
      "htmlFormatted": false,
      "idLookup": false,
      "inlineHelpText": null,
      "label": "Azioni",
      "length": 0,
      "mask": null,
      "maskType": null,
      "name": "Shares",
      "nameField": false,
      "namePointing": false,
      "nillable": true,
      "permissionable": true,
      "picklistValues": [],
      "polymorphicForeignKey": false,
      "precision": 14,
      "queryByDistance": false,
      "referenceTargetField": null,
      "referenceTo": [],
      "relationshipName": null,
      "relationshipOrder": null,
      "restrictedDelete": false,
      "restrictedPicklist": false,
      "scale": 4,
      "searchPrefilterable": false,
      "soapType": "xsd:double",
      "sortable": true,
      "type": "double",
      "unique": false,
      "updateable": true,
      "writeRequiresMasterRead": false
    },
    {
      "aggregatable": true,
      "aiPredictionField": false,
      "autoNumber": false,
      "byteLength": 0,
      "calculated": false,
      "calculatedFormula": null,
      "cascadeDelete": false,
      "caseSensitive": false,
      "compoundFieldName": null,
      "controllerName": null,
      "createable": true,
      "custom": false,
      "defaultValue": null,
      "defaultValueFormula": null,
      "defaultedOnCreate": false,
      "dependentPicklist": false,
      "deprecatedAndHidden": false,
      "digits": 0,
      "displayLocationInDecimal": false,
      "encrypted": false,
      "externalId": false,
      "extraTypeInfo": null,
      "filterable": true,
      "filteredLookupInfo": null,
      "formulaTreatNullNumberAsZero": false,
      "groupable": false,
      "highScaleNumber": false,
      "htmlFormatted": false,
      "idLookup": false,
      "inlineHelpText": null,
      "label": "Prezzo di acquisto",
      "length": 0,
      "mask": null,
      "maskType": null,
      "name": "PurchasePrice",
      "nameField": false,
      "namePointing": false,
      "nillable": true,
      "permissionable": true,
      "picklistValues": [],
      "polymorphicForeignKey": false,
      "precision": 14,
      "queryByDistance": false,
      "referenceTargetField": null,
      "referenceTo": [],
      "relationshipName": null,
      "relationshipOrder": null,
      "restrictedDelete": false,
      "restrictedPicklist": false,
      "scale": 4,
      "searchPrefilterable": false,
      "soapType": "xsd:double",
      "sortable": true,
      "type": "currency",
      "unique": false,
      "updateable": true,
      "writeRequiresMasterRead": false
    },
    {
      "aggregatable": true,
      "aiPredictionField": false,
      "autoNumber": false,
      "byteLength": 0,
      "calculated": false,
      "calculatedFormula": null,
      "cascadeDelete": false,
      "caseSensitive": false,
      "compoundFieldName": null,
      "controllerName": null,
      "createable": true,
      "custom": false,
      "defaultValue": null,
      "defaultValueFormula": null,
      "defaultedOnCreate": false,
      "dependentPicklist": false,
      "deprecatedAndHidden": false,
      "digits": 0,
      "displayLocationInDecimal": false,
      "encrypted": false,
      "externalId": false,
      "extraTypeInfo": null,
      "filterable": true,
      "filteredLookupInfo": null,
      "formulaTreatNullNumberAsZero": false,
      "groupable": false,
      "highScaleNumber": false,
      "htmlFormatted": false,
      "idLookup": false,
      "inlineHelpText": null,
      "label": "Prezzo",
      "length": 0,
      "mask": null,
      "maskType": null,
      "name": "Price",
      "nameField": false,
      "namePointing": false,
      "nillable": true,
      "permissionable": true,
      "picklistValues": [],
      "polymorphicForeignKey": false,
      "precision": 14,
      "queryByDistance": false,
      "referenceTargetField": null,
      "referenceTo": [],
      "relationshipName": null,
      "relationshipOrder": null,
      "restrictedDelete": false,
      "restrictedPicklist": false,
      "scale": 4,
      "searchPrefilterable": false,
      "soapType": "xsd:double",
      "sortable": true,
      "type": "currency",
      "unique": false,
      "updateable": true,
      "writeRequiresMasterRead": false
    },
    {
      "aggregatable": true,
      "aiPredictionField": false,
      "autoNumber": false,
      "byteLength": 0,
      "calculated": false,
      "calculatedFormula": null,
      "cascadeDelete": false,
      "caseSensitive": false,
      "compoundFieldName": null,
      "controllerName": null,
      "createable": true,
      "custom": false,
      "defaultValue": null,
      "defaultValueFormula": null,
      "defaultedOnCreate": false,
      "dependentPicklist": false,
      "deprecatedAndHidden": false,
      "digits": 0,
      "displayLocationInDecimal": false,
      "encrypted": false,
      "externalId": false,
      "extraTypeInfo": null,
      "filterable": true,
      "filteredLookupInfo": null,
      "formulaTreatNullNumberAsZero": false,
      "groupable": false,
      "highScaleNumber": false,
      "htmlFormatted": false,
      "idLookup": false,
      "inlineHelpText": null,
      "label": "Valore di mercato",
      "length": 0,
      "mask": null,
      "maskType": null,
      "name": "MarketValue",
      "nameField": false,
      "namePointing": false,
      "nillable": true,
      "permissionable": true,
      "picklistValues": [],
      "polymorphicForeignKey": false,
      "precision": 18,
      "queryByDistance": false,
      "referenceTargetField": null,
      "referenceTo": [],
      "relationshipName": null,
      "relationshipOrder": null,
      "restrictedDelete": false,
      "restrictedPicklist": false,
      "scale": 2,
      "searchPrefilterable": false,
      "soapType": "xsd:double",
      "sortable": true,
      "type": "currency",
      "unique": false,
      "updateable": true,
      "writeRequiresMasterRead": false
    },
    {
      "aggregatable": true,
      "aiPredictionField": false,
      "autoNumber": false,
      "byteLength": 0,
      "calculated": false,
      "calculatedFormula": null,
      "cascadeDelete": false,
      "caseSensitive": false,
      "compoundFieldName": null,
      "controllerName": null,
      "createable": true,
      "custom": false,
      "defaultValue": null,
      "defaultValueFormula": null,
      "defaultedOnCreate": false,
      "dependentPicklist": false,
      "deprecatedAndHidden": false,
      "digits": 0,
      "displayLocationInDecimal": false,
      "encrypted": false,
      "externalId": false,
      "extraTypeInfo": null,
      "filterable": true,
      "filteredLookupInfo": null,
      "formulaTreatNullNumberAsZero": false,
      "groupable": false,
      "highScaleNumber": false,
      "htmlFormatted": false,
      "idLookup": false,
      "inlineHelpText": null,
      "label": "Variazione percentuale",
      "length": 0,
      "mask": null,
      "maskType": null,
      "name": "PercentChange",
      "nameField": false,
      "namePointing": false,
      "nillable": true,
      "permissionable": true,
      "picklistValues": [],
      "polymorphicForeignKey": false,
      "precision": 16,
      "queryByDistance": false,
      "referenceTargetField": null,
      "referenceTo": [],
      "relationshipName": null,
      "relationshipOrder": null,
      "restrictedDelete": false,
      "restrictedPicklist": false,
      "scale": 2,
      "searchPrefilterable": false,
      "soapType": "xsd:double",
      "sortable": true,
      "type": "percent",
      "unique": false,
      "updateable": true,
      "writeRequiresMasterRead": false
    },
    {
      "aggregatable": true,
      "aiPredictionField": false,
      "autoNumber": false,
      "byteLength": 0,
      "calculated": false,
      "calculatedFormula": null,
      "cascadeDelete": false,
      "caseSensitive": false,
      "compoundFieldName": null,
      "controllerName": null,
      "createable": true,
      "custom": false,
      "defaultValue": null,
      "defaultValueFormula": null,
      "defaultedOnCreate": false,
      "dependentPicklist": false,
      "deprecatedAndHidden": false,
      "digits": 0,
      "displayLocationInDecimal": false,
      "encrypted": false,
      "externalId": false,
      "extraTypeInfo": null,
      "filterable": true,
      "filteredLookupInfo": null,
      "formulaTreatNullNumberAsZero": false,
      "groupable": false,
      "highScaleNumber": false,
      "htmlFormatted": false,
      "idLookup": false,
      "inlineHelpText": null,
      "label": "Ultimo aggiornamento",
      "length": 0,
      "mask": null,
      "maskType": null,
      "name": "LastUpdated",
      "nameField": false,
      "namePointing": false,
      "nillable": true,
      "permissionable": true,
      "picklistValues": [],
      "polymorphicForeignKey": false,
      "precision": 0,
      "queryByDistance": false,
      "referenceTargetField": null,
      "referenceTo": [],
      "relationshipName": null,
      "relationshipOrder": null,
      "restrictedDelete": false,
      "restrictedPicklist": false,
      "scale": 0,
      "searchPrefilterable": false,
      "soapType": "xsd:dateTime",
      "sortable": true,
      "type": "datetime",
      "unique": false,
      "updateable": true,
      "writeRequiresMasterRead": false
    },
    {
      "aggregatable": true,
      "aiPredictionField": false,
      "autoNumber": false,
      "byteLength": 18,
      "calculated": false,
      "calculatedFormula": null,
      "cascadeDelete": false,
      "caseSensitive": false,
      "compoundFieldName": null,
      "controllerName": null,
      "createable": true,
      "custom": false,
      "defaultValue": null,
      "defaultValueFormula": null,
      "defaultedOnCreate": false,
      "dependentPicklist": false,
      "deprecatedAndHidden": false,
      "digits": 0,
      "displayLocationInDecimal": false,
      "encrypted": false,
      "externalId": false,
      "extraTypeInfo": null,
      "filterable": true,
      "filteredLookupInfo": null,
      "formulaTreatNullNumberAsZero": false,
      "groupable": true,
      "highScaleNumber": false,
      "htmlFormatted": false,
      "idLookup": false,
      "inlineHelpText": null,
      "label": "ID account",
      "length": 18,
      "mask": null,
      "maskType": null,
      "name": "HouseholdId",
      "nameField": false,
      "namePointing": false,
      "nillable": true,
      "permissionable": true,
      "picklistValues": [],
      "polymorphicForeignKey": false,
      "precision": 0,
      "queryByDistance": false,
      "referenceTargetField": null,
      "referenceTo": [
        "Account"
      ],
      "relationshipName": "Household",
      "relationshipOrder": null,
      "restrictedDelete": false,
      "restrictedPicklist": false,
      "scale": 0,
      "searchPrefilterable": true,
      "soapType": "tns:ID",
      "sortable": true,
      "type": "reference",
      "unique": false,
      "updateable": true,
      "writeRequiresMasterRead": false
    },
    {
      "aggregatable": true,
      "aiPredictionField": false,
      "autoNumber": false,
      "byteLength": 0,
      "calculated": false,
      "calculatedFormula": null,
      "cascadeDelete": false,
      "caseSensitive": false,
      "compoundFieldName": null,
      "controllerName": null,
      "createable": true,
      "custom": false,
      "defaultValue": null,
      "defaultValueFormula": null,
      "defaultedOnCreate": false,
      "dependentPicklist": false,
      "deprecatedAndHidden": false,
      "digits": 0,
      "displayLocationInDecimal": false,
      "encrypted": false,
      "externalId": false,
      "extraTypeInfo": null,
      "filterable": true,
      "filteredLookupInfo": null,
      "formulaTreatNullNumberAsZero": false,
      "groupable": false,
      "highScaleNumber": false,
      "htmlFormatted": false,
      "idLookup": false,
      "inlineHelpText": null,
      "label": "Utile/Perdita",
      "length": 0,
      "mask": null,
      "maskType": null,
      "name": "GainLoss",
      "nameField": false,
      "namePointing": false,
      "nillable": true,
      "permissionable": true,
      "picklistValues": [],
      "polymorphicForeignKey": false,
      "precision": 18,
      "queryByDistance": false,
      "referenceTargetField": null,
      "referenceTo": [],
      "relationshipName": null,
      "relationshipOrder": null,
      "restrictedDelete": false,
      "restrictedPicklist": false,
      "scale": 2,
      "searchPrefilterable": false,
      "soapType": "xsd:double",
      "sortable": true,
      "type": "currency",
      "unique": false,
      "updateable": true,
      "writeRequiresMasterRead": false
    },
    {
      "aggregatable": true,
      "aiPredictionField": false,
      "autoNumber": false,
      "byteLength": 765,
      "calculated": false,
      "calculatedFormula": null,
      "cascadeDelete": false,
      "caseSensitive": false,
      "compoundFieldName": null,
      "controllerName": null,
      "createable": true,
      "custom": false,
      "defaultValue": null,
      "defaultValueFormula": null,
      "defaultedOnCreate": false,
      "dependentPicklist": false,
      "deprecatedAndHidden": false,
      "digits": 0,
      "displayLocationInDecimal": false,
      "encrypted": false,
      "externalId": false,
      "extraTypeInfo": null,
      "filterable": true,
      "filteredLookupInfo": null,
      "formulaTreatNullNumberAsZero": false,
      "groupable": true,
      "highScaleNumber": false,
      "htmlFormatted": false,
      "idLookup": true,
      "inlineHelpText": null,
      "label": "Identificatore sistema di origine",
      "length": 255,
      "mask": null,
      "maskType": null,
      "name": "SourceSystemIdentifier",
      "nameField": false,
      "namePointing": false,
      "nillable": true,
      "permissionable": true,
      "picklistValues": [],
      "polymorphicForeignKey": false,
      "precision": 0,
      "queryByDistance": false,
      "referenceTargetField": null,
      "referenceTo": [],
      "relationshipName": null,
      "relationshipOrder": null,
      "restrictedDelete": false,
      "restrictedPicklist": false,
      "scale": 0,
      "searchPrefilterable": false,
      "soapType": "xsd:string",
      "sortable": true,
      "type": "string",
      "unique": true,
      "updateable": true,
      "writeRequiresMasterRead": false
    },
    {
      "aggregatable": true,
      "aiPredictionField": false,
      "autoNumber": false,
      "byteLength": 765,
      "calculated": false,
      "calculatedFormula": null,
      "cascadeDelete": false,
      "caseSensitive": false,
      "compoundFieldName": null,
      "controllerName": null,
      "createable": true,
      "custom": false,
      "defaultValue": null,
      "defaultValueFormula": null,
      "defaultedOnCreate": false,
      "dependentPicklist": false,
      "deprecatedAndHidden": false,
      "digits": 0,
      "displayLocationInDecimal": false,
      "encrypted": false,
      "externalId": false,
      "extraTypeInfo": null,
      "filterable": true,
      "filteredLookupInfo": null,
      "formulaTreatNullNumberAsZero": false,
      "groupable": true,
      "highScaleNumber": false,
      "htmlFormatted": false,
      "idLookup": false,
      "inlineHelpText": null,
      "label": "Sistema di origine",
      "length": 255,
      "mask": null,
      "maskType": null,
      "name": "SourceSystem",
      "nameField": false,
      "namePointing": false,
      "nillable": true,
      "permissionable": true,
      "picklistValues": [],
      "polymorphicForeignKey": false,
      "precision": 0,
      "queryByDistance": false,
      "referenceTargetField": null,
      "referenceTo": [],
      "relationshipName": null,
      "relationshipOrder": null,
      "restrictedDelete": false,
      "restrictedPicklist": false,
      "scale": 0,
      "searchPrefilterable": false,
      "soapType": "xsd:string",
      "sortable": true,
      "type": "string",
      "unique": false,
      "updateable": true,
      "writeRequiresMasterRead": false
    }
  ],
  "hasSubtypes": false,
  "implementedBy": null,
  "implementsInterfaces": null,
  "isInterface": false,
  "isSubtype": false,
  "keyPrefix": "0eX",
  "label": "Portafoglio titoli",
  "labelPlural": "Portafogli titoli",
  "layoutable": true,
  "listviewable": null,
  "lookupLayoutable": null,
  "mergeable": false,
  "mruEnabled": true,
  "name": "SecuritiesHolding",
  "namedLayoutInfos": [],
  "networkScopeFieldName": null,
  "queryable": true,
  "recordTypeInfos": [
    {
      "active": true,
      "available": true,
      "defaultRecordTypeMapping": true,
      "developerName": "Principale",
      "master": true,
      "name": "Principale",
      "recordTypeId": "012000000000000AAA",
      "urls": {
        "layout": "/services/data/v56.0/sobjects/SecuritiesHolding/describe/layouts/012000000000000AAA"
      }
    }
  ],
  "replicateable": true,
  "retrieveable": true,
  "searchLayoutable": true,
  "searchable": true,
  "sobjectDescribeOption": "FULL",
  "supportedScopes": [
    {
      "label": "Tutti i portafogli titoli",
      "name": "everything"
    },
    {
      "label": "Portafogli titoli personali",
      "name": "mine"
    },
    {
      "label": "Portafogli titoli di proprietà dell'area di attesa",
      "name": "queue_owned"
    },
    {
      "label": "Portafogli titoli del team personale",
      "name": "team"
    },
    {
      "label": "Portafogli titoli di proprietà dell'utente",
      "name": "user_owned"
    }
  ],
  "triggerable": true,
  "undeletable": true,
  "updateable": true,
  "urls": {
    "compactLayouts": "/services/data/v56.0/sobjects/SecuritiesHolding/describe/compactLayouts",
    "rowTemplate": "/services/data/v56.0/sobjects/SecuritiesHolding/{ID}",
    "approvalLayouts": "/services/data/v56.0/sobjects/SecuritiesHolding/describe/approvalLayouts",
    "uiDetailTemplate": "https://flow-flow-8123.scratch.my.salesforce.com/{ID}",
    "uiEditTemplate": "https://flow-flow-8123.scratch.my.salesforce.com/{ID}/e",
    "describe": "/services/data/v56.0/sobjects/SecuritiesHolding/describe",
    "uiNewRecord": "https://flow-flow-8123.scratch.my.salesforce.com/0eX/e",
    "quickActions": "/services/data/v56.0/sobjects/SecuritiesHolding/quickActions",
    "layouts": "/services/data/v56.0/sobjects/SecuritiesHolding/describe/layouts",
    "sobject": "/services/data/v56.0/sobjects/SecuritiesHolding"
  }
}
